{
  "indexed": {
    "date-parts": [
      [
        2026,
        1,
        27
      ]
    ],
    "date-time": "2026-01-27T09:54:22Z",
    "timestamp": 1769507662784,
    "version": "3.49.0"
  },
  "reference-count": 62,
  "publisher": "FapUNIFESP (SciELO)",
  "issue": "5",
  "content-domain": {
    "domain": [],
    "crossmark-restriction": false
  },
  "short-container-title": [
    "Rev. Saúde Pública"
  ],
  "published-print": {
    "date-parts": [
      [
        2000,
        10
      ]
    ]
  },
  "abstract": "<jats:p>A área de avaliação de programas, serviços e tecnologias em geral e na saúde, em particular, passa por um processo de expansão e diversificação conceitual e metodológica, bem como por uma crescente demanda para se constituir em instrumento de apoio às decisões necessárias à dinâmica dos sistemas e serviços de saúde, na implementação das políticas de saúde. Apoiando-se em uma revisão da literatura internacional especializada, e tomando por referência a década de 90, foram identificados os critérios nucleares que organizam os processos de avaliação, articulando-os com os recortes adotados pelas principais tipologias de avaliação, atualmente institucionalizadas nos países desenvolvidos, avaliação de programas, avaliação e garantia de qualidade em serviços e avaliação de tecnologias. A participação brasileira no desenvolvimento metodológico da área também é analisada.</jats:p>",
  "DOI": "10.1590/s0034-89102000000500018",
  "type": "journal-article",
  "created": {
    "date-parts": [
      [
        2005,
        4,
        27
      ]
    ],
    "date-time": "2005-04-27T14:19:08Z",
    "timestamp": 1114611548000
  },
  "page": "547-549",
  "source": "Crossref",
  "is-referenced-by-count": 98,
  "title": [
    "Avaliação de programas, serviços e tecnologias em saúde"
  ],
  "prefix": "10.1590",
  "volume": "34",
  "author": [
    {
      "given": "Hillegonda Maria D",
      "family": "Novaes",
      "sequence": "first",
      "affiliation": [
        {
          "name": "Universidade de São Paulo, Brasil"
        }
      ]
    }
  ],
  "member": "530",
  "reference": [
    {
      "key": "ref1",
      "series-title": "Translating evidence into practice 1997: conference summary",
      "year": "1998"
    },
    {
      "key": "ref2",
      "series-title": "Avaliação de serviços e programas sociais",
      "author": "Aguilar MJ",
      "year": "1994"
    },
    {
      "key": "ref3",
      "doi-asserted-by": "crossref",
      "first-page": "283",
      "DOI": "10.1136/bmj.308.6924.283",
      "article-title": "The scandal of poor medical research",
      "volume": "308",
      "author": "Altman D",
      "year": "1994",
      "journal-title": "BMJ",
      "ISSN": "https://id.crossref.org/issn/0959-8138",
      "issn-type": "print"
    },
    {
      "issue": "3",
      "key": "ref4",
      "article-title": "Avaliação tecnológica em saúde",
      "year": "1991",
      "journal-title": "Divulg Saúde Debate"
    },
    {
      "key": "ref5",
      "series-title": "Health care technology and its assessment: an international perspective",
      "author": "Banta HD",
      "year": "1993"
    },
    {
      "key": "ref6",
      "doi-asserted-by": "crossref",
      "first-page": "430",
      "DOI": "10.1017/S0266462300010692",
      "article-title": "A History of ISTAHC: A personal perspective on its first 10 years",
      "volume": "13",
      "author": "Banta HD",
      "year": "1997",
      "journal-title": "Int J Technol Assess Health Care",
      "ISSN": "https://id.crossref.org/issn/0266-4623",
      "issn-type": "print"
    },
    {
      "key": "ref7",
      "series-title": "The organization of health care technology assessment in the Netherlands",
      "author": "Banta HD",
      "year": "1995"
    },
    {
      "key": "ref8",
      "doi-asserted-by": "crossref",
      "first-page": "287",
      "DOI": "10.1017/S0266462300006905",
      "article-title": "The development of health care technology assessment: an international perspective",
      "volume": "11",
      "author": "Battista RN",
      "year": "1995",
      "journal-title": "Int J Technol Assess Health Care",
      "ISSN": "https://id.crossref.org/issn/0266-4623",
      "issn-type": "print"
    },
    {
      "key": "ref9",
      "series-title": "Beyond objectivism and relativism: science, hermeneutics and praxis",
      "author": "Bernstein RJ",
      "year": "1983"
    },
    {
      "key": "ref10",
      "doi-asserted-by": "crossref",
      "first-page": "35",
      "DOI": "10.3138/cjpe.11.002",
      "article-title": "Getting on and off the policy agenda: a dualistic theory of program evaluation utilization",
      "volume": "11",
      "author": "Cabatoff KA",
      "year": "1996",
      "journal-title": "Can J Program Eval"
    },
    {
      "key": "ref11",
      "series-title": "A fabricação da ciência",
      "author": "Chalmers A",
      "year": "1994"
    },
    {
      "key": "ref12",
      "series-title": "Theory-driven evaluations",
      "author": "Chen HT",
      "year": "1990"
    },
    {
      "key": "ref13",
      "series-title": "Avaliação em saúde",
      "first-page": "29",
      "volume-title": "A avaliação na área da saúde: conceitos e métodos",
      "author": "Contandriopoulos A-P",
      "year": "1997"
    },
    {
      "key": "ref14",
      "series-title": "Handbook of qualitative research",
      "author": "Denzin NK",
      "year": "1994"
    },
    {
      "key": "ref15",
      "first-page": "9",
      "article-title": "Continuity and change in the quest for quality",
      "volume": "1",
      "author": "Donabedian A",
      "year": "1996",
      "journal-title": "Clin Perform Qual Health Care",
      "ISSN": "https://id.crossref.org/issn/1063-0279",
      "issn-type": "print"
    },
    {
      "key": "ref16",
      "doi-asserted-by": "crossref",
      "first-page": "99",
      "DOI": "10.1016/S0097-5990(16)30021-5",
      "article-title": "Criteria and standards for quality assessment and monitoring",
      "volume": "12",
      "author": "Donabedian A",
      "year": "1986",
      "journal-title": "Qual Rev Bull"
    },
    {
      "key": "ref17",
      "doi-asserted-by": "crossref",
      "first-page": "487",
      "DOI": "10.1017/S0266462300007571",
      "article-title": "The assessment of technology and quality",
      "volume": "4",
      "author": "Donabedian A",
      "year": "1988",
      "journal-title": "Int J Technol Assess Health Care",
      "ISSN": "https://id.crossref.org/issn/0266-4623",
      "issn-type": "print"
    },
    {
      "key": "ref18",
      "doi-asserted-by": "crossref",
      "first-page": "1743",
      "DOI": "10.1001/jama.1988.03410120089033",
      "article-title": "The quality of care: How can it be assessed?",
      "volume": "260",
      "author": "Donabedian A",
      "year": "1988",
      "journal-title": "JAMA",
      "ISSN": "https://id.crossref.org/issn/0098-7484",
      "issn-type": "print"
    },
    {
      "key": "ref19",
      "doi-asserted-by": "crossref",
      "first-page": "356",
      "DOI": "10.1016/S0097-5990(16)30560-7",
      "article-title": "The role of outcomes in quality assessment and assurance",
      "volume": "18",
      "author": "Donabedian A",
      "year": "1992",
      "journal-title": "Qual Rev Bull"
    },
    {
      "key": "ref20",
      "first-page": "1115",
      "article-title": "The seven pillars of quality",
      "volume": "114",
      "author": "Donabedian A",
      "year": "1990",
      "journal-title": "Arch Pathol Lab Med",
      "ISSN": "https://id.crossref.org/issn/0003-9985",
      "issn-type": "print"
    },
    {
      "key": "ref21",
      "series-title": "Methods for the economic evaluation of health care programmes",
      "author": "Drummond MF",
      "year": "1997"
    },
    {
      "issue": "suppl 5",
      "key": "ref22",
      "first-page": "MS1",
      "article-title": "Health care cost-benefit and cost-effectiveness analysis: an update",
      "volume": "36",
      "author": "Elixhauser A",
      "year": "1998",
      "journal-title": "Med Care",
      "ISSN": "https://id.crossref.org/issn/0025-7079",
      "issn-type": "print"
    },
    {
      "key": "ref23",
      "article-title": "Epidemiologia e avaliação de serviços de saúde",
      "volume": "12",
      "year": "1996",
      "journal-title": "Cad Saúde Pública"
    },
    {
      "key": "ref24",
      "doi-asserted-by": "crossref",
      "first-page": "1365",
      "DOI": "10.1016/0277-9536(94)00272-U",
      "article-title": "Dealing with uncertainty: will science solve the problems of resource allocation in the U K NHS?",
      "volume": "40",
      "author": "Freemantle N",
      "year": "1995",
      "journal-title": "Soc Sci Med",
      "ISSN": "https://id.crossref.org/issn/0037-7856",
      "issn-type": "print"
    },
    {
      "key": "ref25",
      "series-title": "Thinking things through: an introduction to philosophical issues and achievements",
      "author": "Glymour C",
      "year": "1992"
    },
    {
      "key": "ref26",
      "doi-asserted-by": "crossref",
      "first-page": "335",
      "DOI": "10.1017/S0266462300013568",
      "article-title": "It's time to rethink health care technology assessment",
      "volume": "8",
      "author": "Goodman C",
      "year": "1992",
      "journal-title": "Int J Technol Assess Health Care",
      "ISSN": "https://id.crossref.org/issn/0266-4623",
      "issn-type": "print"
    },
    {
      "key": "ref27",
      "series-title": "Handbook of qualitative research",
      "first-page": "531",
      "volume-title": "Qualitative program evaluation: practice and promise",
      "author": "Greene JC",
      "year": "1994"
    },
    {
      "key": "ref28",
      "series-title": "Fourth generation evaluation",
      "author": "Guba EG",
      "year": "1989"
    },
    {
      "key": "ref29",
      "doi-asserted-by": "crossref",
      "first-page": "229",
      "DOI": "10.1590/S0102-311X1999000200002",
      "article-title": "Institutionalizing the evaluation of health programs and policies in France: cuisine internationale over fast food and sur mesure over ready-made",
      "volume": "15",
      "author": "Hartz ZMA",
      "year": "1999",
      "journal-title": "Cad Saúde Pública"
    },
    {
      "key": "ref30",
      "series-title": "Avaliação em saúde: dos modelos conceituais à prática na análise da implantação de programas",
      "author": "Hartz ZMA",
      "year": "1997"
    },
    {
      "key": "ref31",
      "series-title": "Evaluating with validity",
      "author": "House ER",
      "year": "1980"
    },
    {
      "key": "ref32",
      "series-title": "Controle da qualidade total à maneira japonesa",
      "author": "Ishikawa K",
      "year": "1993"
    },
    {
      "key": "ref33",
      "doi-asserted-by": "crossref",
      "first-page": "79",
      "DOI": "10.1017/S0266462300005274",
      "article-title": "The use of technology assessment by hospitals, health maintenance organizations and third party payers in the United States",
      "volume": "11",
      "author": "Luce BR",
      "year": "1995",
      "journal-title": "Int J Technol Assess Health Care",
      "ISSN": "https://id.crossref.org/issn/0266-4623",
      "issn-type": "print"
    },
    {
      "key": "ref34",
      "doi-asserted-by": "crossref",
      "first-page": "32",
      "DOI": "10.1590/S0034-75901992000400004",
      "article-title": "Desenvolvimento de recursos humanos, gerência de qualidade e cultura das organizações de saúde",
      "volume": "32",
      "author": "Malik AM",
      "year": "1992",
      "journal-title": "Rev Adm Empres"
    },
    {
      "key": "ref35",
      "first-page": "7",
      "article-title": "Qualidade em serviços de saúde nos setores público e privado",
      "volume": "19",
      "author": "Malik AM",
      "year": "1996",
      "journal-title": "Cad Fundap"
    },
    {
      "key": "ref36",
      "series-title": "Qualitative data analysis",
      "author": "Miles MB",
      "year": "1994"
    },
    {
      "key": "ref37",
      "series-title": "O desafio do conhecimento: pesquisa qualitativa em saúde",
      "author": "Minayo MCS",
      "year": "1992"
    },
    {
      "key": "ref38",
      "series-title": "Impact analysis for program evaluation",
      "author": "Mohr LB",
      "year": "1995"
    },
    {
      "key": "ref39",
      "series-title": "Perspectivas da qualidade em saúde",
      "author": "Nogueira RP",
      "year": "1994"
    },
    {
      "key": "ref40",
      "series-title": "Padrões e indicadores de qualidade para hospitais (Brasil)",
      "author": "Novaes HM",
      "year": "1994"
    },
    {
      "key": "ref41",
      "series-title": "A puericultura em questão",
      "author": "Novaes HMD"
    },
    {
      "issue": "12",
      "key": "ref42",
      "doi-asserted-by": "crossref",
      "first-page": "7",
      "DOI": "10.1590/S0102-311X1996000600002",
      "article-title": "Epidemiologia e avaliação em serviços de atenção médica: novas tendências de pesquisa",
      "author": "Novaes HMD",
      "year": "1996",
      "journal-title": "Cad Saúde Pública"
    },
    {
      "key": "ref43",
      "doi-asserted-by": "crossref",
      "first-page": "24",
      "DOI": "10.1590/S0104-59701996000100003",
      "article-title": "Sobre a técnica",
      "volume": "3",
      "author": "Novaes RL",
      "year": "1996",
      "journal-title": "Hist Ciênc Saúde"
    },
    {
      "key": "ref44",
      "series-title": "Health technology assessment methodologies for developing countries",
      "author": "Panerai RB",
      "year": "1989"
    },
    {
      "key": "ref45",
      "series-title": "Sciences exactes et sciences de l\"homme: les grandes étapes",
      "author": "Parrochia D",
      "year": "1997"
    },
    {
      "key": "ref46",
      "series-title": "Utilization-focused evaluation",
      "author": "Patton MQ",
      "year": "1997"
    },
    {
      "key": "ref47",
      "doi-asserted-by": "crossref",
      "first-page": "81",
      "DOI": "10.1017/S0266462300010254",
      "article-title": "The status of health technology assessment worldwide",
      "volume": "13",
      "author": "Perry S",
      "year": "1997",
      "journal-title": "Int J Technol Assess Health Care",
      "ISSN": "https://id.crossref.org/issn/0266-4623",
      "issn-type": "print"
    },
    {
      "key": "ref48",
      "series-title": "Filosofia, história e sociologia das ciências",
      "author": "Portocarrero V",
      "year": "1994"
    },
    {
      "issue": "19",
      "key": "ref49",
      "article-title": "Qualidade em saúde",
      "year": "1996",
      "journal-title": "Cad Fundap"
    },
    {
      "key": "ref50",
      "series-title": "The web of belief",
      "author": "Quine WV",
      "year": "1970"
    },
    {
      "key": "ref51",
      "first-page": "25",
      "article-title": "Planejamento estratégico-situacional ou controle de qualidade total em saúde?: Um contraponto teórico-metodológico",
      "volume": "19",
      "author": "Rivera FJU",
      "year": "1996",
      "journal-title": "Cad Fundap"
    },
    {
      "key": "ref52",
      "series-title": "Causal inference",
      "author": "Rothman K",
      "year": "1988"
    },
    {
      "key": "ref53",
      "series-title": "Evaluation: a systematic approach",
      "author": "Rossi PH",
      "year": "1993"
    },
    {
      "key": "ref54",
      "series-title": "Using clinical practice guidelines to evaluate quality of care",
      "author": "Schoenbaum SC",
      "year": "1995"
    },
    {
      "key": "ref55",
      "series-title": "Accreditation",
      "author": "Scrivens E",
      "year": "1995"
    },
    {
      "key": "ref56",
      "series-title": "Health program evaluation",
      "author": "Shortell SM",
      "year": "1978"
    },
    {
      "key": "ref57",
      "doi-asserted-by": "crossref",
      "first-page": "80",
      "DOI": "10.1590/S0102-311X1994000100009",
      "article-title": "Avaliação em saúde: limites e perspectivas",
      "volume": "10",
      "author": "Silva LMV",
      "year": "1994",
      "journal-title": "Cad Saúde Pública"
    },
    {
      "key": "ref58",
      "series-title": "A temática da avaliação no campo de saúde coletiva: uma bibliografia comentada",
      "author": "Stenzel ACB"
    },
    {
      "key": "ref59",
      "series-title": "An UNICEF guide for monitoring and evaluation",
      "year": "1998"
    },
    {
      "key": "ref60",
      "series-title": "L'etat des sciences",
      "author": "Witkowski N",
      "year": "1991"
    },
    {
      "key": "ref61",
      "series-title": "Rapid evaluation method: guidelines for maternal and child health, family planning and other health services",
      "year": "1993"
    },
    {
      "key": "ref62",
      "series-title": "Analyzing costs, procedures, processes and outcome in human services",
      "author": "Yates BT",
      "year": "1996"
    }
  ],
  "container-title": [
    "Revista de Saúde Pública"
  ],
  "original-title": [],
  "link": [
    {
      "URL": "http://www.scielo.br/pdf/rsp/v34n5/3227.pdf",
      "content-type": "unspecified",
      "content-version": "vor",
      "intended-application": "similarity-checking"
    }
  ],
  "deposited": {
    "date-parts": [
      [
        2024,
        12,
        31
      ]
    ],
    "date-time": "2024-12-31T22:45:13Z",
    "timestamp": 1735685113000
  },
  "score": 1,
  "resource": {
    "primary": {
      "URL": "http://www.scielo.br/scielo.php?script=sci_arttext&pid=S0034-89102000000500018&lng=pt&tlng=pt"
    }
  },
  "subtitle": [],
  "short-title": [],
  "issued": {
    "date-parts": [
      [
        2000,
        10
      ]
    ]
  },
  "references-count": 62,
  "journal-issue": {
    "issue": "5",
    "published-print": {
      "date-parts": [
        [
          2000,
          10
        ]
      ]
    }
  },
  "alternative-id": [
    "S0034-89102000000500018"
  ],
  "URL": "https://doi.org/10.1590/s0034-89102000000500018",
  "relation": {},
  "ISSN": [
    "0034-8910"
  ],
  "issn-type": [
    {
      "value": "0034-8910",
      "type": "electronic"
    }
  ],
  "subject": [],
  "published": {
    "date-parts": [
      [
        2000,
        10
      ]
    ]
  }
}