{
  "indexed": {
    "date-parts": [
      [
        2026,
        1,
        14
      ]
    ],
    "date-time": "2026-01-14T19:03:30Z",
    "timestamp": 1768417410456,
    "version": "3.49.0"
  },
  "reference-count": 42,
  "publisher": "MDPI AG",
  "issue": "18",
  "license": [
    {
      "start": {
        "date-parts": [
          [
            2020,
            9,
            22
          ]
        ],
        "date-time": "2020-09-22T00:00:00Z",
        "timestamp": 1600732800000
      },
      "content-version": "vor",
      "delay-in-days": 0,
      "URL": "https://creativecommons.org/licenses/by/4.0/"
    }
  ],
  "content-domain": {
    "domain": [],
    "crossmark-restriction": false
  },
  "short-container-title": [
    "IJERPH"
  ],
  "abstract": "<jats:p>Since its post-World War II inception, the science of record linkage has grown exponentially and is used across industrial, governmental, and academic agencies. The academic fields that rely on record linkage are diverse, ranging from history to public health to demography. In this paper, we introduce the different types of data linkage and give a historical context to their development. We then introduce the three types of underlying models for probabilistic record linkage: Fellegi-Sunter-based methods, machine learning methods, and Bayesian methods. Practical considerations, such as data standardization and privacy concerns, are then discussed. Finally, recommendations are given for organizations developing or maintaining record linkage programs, with an emphasis on organizations measuring long-term complications of disasters, such as 9/11.</jats:p>",
  "DOI": "10.3390/ijerph17186937",
  "type": "journal-article",
  "created": {
    "date-parts": [
      [
        2020,
        9,
        23
      ]
    ],
    "date-time": "2020-09-23T09:28:08Z",
    "timestamp": 1600853288000
  },
  "page": "6937",
  "update-policy": "https://doi.org/10.3390/mdpi_crossmark_policy",
  "source": "Crossref",
  "is-referenced-by-count": 22,
  "title": [
    "An Introduction to Probabilistic Record Linkage with a Focus on Linkage Processing for WTC Registries"
  ],
  "prefix": "10.3390",
  "volume": "17",
  "author": [
    {
      "ORCID": "https://orcid.org/0000-0003-0559-0372",
      "authenticated-orcid": false,
      "given": "Jana",
      "family": "Asher",
      "sequence": "first",
      "affiliation": [
        {
          "name": "Department of Mathematics and Statistics, Slippery Rock University, Slippery Rock, PA 16057, USA"
        }
      ]
    },
    {
      "given": "Dean",
      "family": "Resnick",
      "sequence": "additional",
      "affiliation": [
        {
          "name": "National Opinion Research Center, Boston, MA 02114, USA"
        }
      ]
    },
    {
      "given": "Jennifer",
      "family": "Brite",
      "sequence": "additional",
      "affiliation": [
        {
          "name": "Division of Epidemiology, New York City Department of Health and Mental Hygiene, World Trade Center Health Registry, New York, NY 11101, USA"
        }
      ]
    },
    {
      "given": "Robert",
      "family": "Brackbill",
      "sequence": "additional",
      "affiliation": [
        {
          "name": "Division of Epidemiology, New York City Department of Health and Mental Hygiene, World Trade Center Health Registry, New York, NY 11101, USA"
        }
      ]
    },
    {
      "given": "James",
      "family": "Cone",
      "sequence": "additional",
      "affiliation": [
        {
          "name": "Division of Epidemiology, New York City Department of Health and Mental Hygiene, World Trade Center Health Registry, New York, NY 11101, USA"
        }
      ]
    }
  ],
  "member": "1968",
  "published-online": {
    "date-parts": [
      [
        2020,
        9,
        22
      ]
    ]
  },
  "reference": [
    {
      "key": "ref_1",
      "doi-asserted-by": "crossref",
      "first-page": "301",
      "DOI": "10.2307/347835",
      "article-title": "Falsification of Age at Marriage",
      "volume": "15",
      "author": "Christensen",
      "year": "1953",
      "journal-title": "Marriage Fam. Living"
    },
    {
      "key": "ref_2",
      "doi-asserted-by": "crossref",
      "first-page": "1412",
      "DOI": "10.2105/AJPH.36.12.1412",
      "article-title": "Record linkage",
      "volume": "36",
      "author": "Dunn",
      "year": "1946",
      "journal-title": "Am. J. Publ. Health Nations Health"
    },
    {
      "key": "ref_3",
      "doi-asserted-by": "crossref",
      "first-page": "451",
      "DOI": "10.1086/636025",
      "article-title": "Some observations on the Canadian family allowances program",
      "volume": "20",
      "author": "Schwartz",
      "year": "1946",
      "journal-title": "Soc. Serv Rev."
    },
    {
      "key": "ref_4",
      "doi-asserted-by": "crossref",
      "first-page": "204",
      "DOI": "10.1080/00324728.1947.10415531",
      "article-title": "Canada’s national vital statistics index",
      "volume": "1",
      "author": "Marshall",
      "year": "1947",
      "journal-title": "Popul. Stud."
    },
    {
      "key": "ref_5",
      "unstructured": "Barrai, I., Cavalli-Sforza, L.L., and Moroni, A. (1965). Record linkage from parish books. Mathematics and Computer Science in Biology and Medicine, John Blackburn Ltd."
    },
    {
      "key": "ref_6",
      "unstructured": "Shryock, H.S. (1957). Development of postcensal population estimates for local areas. Regional Income, Proceedings of the Conference on Research in Income and Wealth, Durham, NC, USA, 17–18 June 1955, Princeton University Press."
    },
    {
      "key": "ref_7",
      "doi-asserted-by": "crossref",
      "first-page": "954",
      "DOI": "10.1126/science.130.3381.954",
      "article-title": "Automatic linkage of vital records",
      "volume": "130",
      "author": "Newcombe",
      "year": "1959",
      "journal-title": "Science"
    },
    {
      "key": "ref_8",
      "first-page": "8",
      "article-title": "Oxford record linkage study: A central file of morbidity and mortality records for a pilot population",
      "volume": "18",
      "author": "Acheson",
      "year": "1964",
      "journal-title": "Br. J. Prev Soc. Med."
    },
    {
      "key": "ref_9",
      "doi-asserted-by": "crossref",
      "first-page": "369",
      "DOI": "10.1001/archpsyc.1963.01720160059007",
      "article-title": "All psychiatric experience in a community: A cumulative survey: Report of the first years’ experience",
      "volume": "9",
      "author": "Gardner",
      "year": "1963",
      "journal-title": "Arch. Gen. Psychiatry"
    },
    {
      "key": "ref_10",
      "unstructured": "Phillips, W., and Bahn, A.K. (1963, January 4–7). Experience with computer matching of names. Proceedings of the American Statistical Association, Social Statistics Section, Cleveland, OH, USA."
    },
    {
      "key": "ref_11",
      "doi-asserted-by": "crossref",
      "first-page": "1183",
      "DOI": "10.1080/01621459.1969.10501049",
      "article-title": "A theory for record linkage",
      "volume": "64",
      "author": "Fellegi",
      "year": "1969",
      "journal-title": "J. Am. Stat. Assoc."
    },
    {
      "key": "ref_12",
      "first-page": "766",
      "article-title": "Methods of record-linkage and applications in Israel",
      "volume": "41",
      "author": "Bachi",
      "year": "1967",
      "journal-title": "Bull. Int. Stat. Inst."
    },
    {
      "key": "ref_13",
      "doi-asserted-by": "crossref",
      "first-page": "375",
      "DOI": "10.1016/0021-9681(70)90020-2",
      "article-title": "Health statistics and record linkage in Australia",
      "volume": "23",
      "author": "Hobbs",
      "year": "1970",
      "journal-title": "J. Chronic Dis."
    },
    {
      "key": "ref_14",
      "first-page": "3",
      "article-title": "Data cleaning: Problems and current approaches",
      "volume": "23",
      "author": "Rahm",
      "year": "2000",
      "journal-title": "IEEE Data Eng. Bull."
    },
    {
      "key": "ref_15",
      "unstructured": "(2019, October 24). Howmanyofme.com. Available online: http://howmanyofme.com/."
    },
    {
      "key": "ref_16",
      "unstructured": "Winkler, W.E. (1990, January 6–9). String Comparator Metrics and Enhanced Decision Rules in the Fellegi-Sunter Model of Record Linkage. Proceedings of the American Statistical Association, Section on Survey Research Methods, Anaheim, CA, USA."
    },
    {
      "key": "ref_17",
      "doi-asserted-by": "crossref",
      "first-page": "1",
      "DOI": "10.1016/S0020-0255(00)00070-0",
      "article-title": "Efficient data reconciliation",
      "volume": "137",
      "author": "Cochinwala",
      "year": "2001",
      "journal-title": "Inform. Sci."
    },
    {
      "key": "ref_18",
      "unstructured": "Bilenko, M., and Mooney, R.J. (2003, January 24–27). 1. On Evaluation and Training-Set Construction for Duplicate Detection. Proceedings of the KDD-03 Workshop on Data Cleaning, Record Linkage, and Object Consolidation, Washington, DC, USA."
    },
    {
      "key": "ref_19",
      "doi-asserted-by": "crossref",
      "unstructured": "Chen, F., Gao, B.J., Doan, A., Yang, J., and Ramakrishnan, R. (July, January 29). Optimizing complex extraction programs over evolving text data. Proceedings of the 2009 ACM SIGMOD International Conference on Management of data, Providence, RI, USA.",
      "DOI": "10.1145/1559845.1559881"
    },
    {
      "key": "ref_20",
      "doi-asserted-by": "crossref",
      "first-page": "289",
      "DOI": "10.14778/1687627.1687661",
      "article-title": "Answering table augmentation queries from unstructured lists on the web",
      "volume": "2",
      "author": "Gupta",
      "year": "2009",
      "journal-title": "Proc. VLDB Endow."
    },
    {
      "key": "ref_21",
      "first-page": "707",
      "article-title": "Binary codes capable of correcting deletions, insertions, and reversals",
      "volume": "10",
      "author": "Levenshtein",
      "year": "1966",
      "journal-title": "Sov. Phys. Dokl."
    },
    {
      "key": "ref_22",
      "doi-asserted-by": "crossref",
      "first-page": "171",
      "DOI": "10.1145/363958.363994",
      "article-title": "A technique for computer detection and correction of spelling errors",
      "volume": "7",
      "author": "Damerau",
      "year": "1964",
      "journal-title": "Commun. ACM"
    },
    {
      "key": "ref_23",
      "doi-asserted-by": "crossref",
      "first-page": "8",
      "DOI": "10.1016/j.cogsys.2016.01.001",
      "article-title": "CoTO: A novel approach for fuzzy aggregation of semantic similarity measures",
      "volume": "40",
      "year": "2016",
      "journal-title": "Cogn. Syst. Res."
    },
    {
      "key": "ref_24",
      "unstructured": "Liseo, B., and Tancredi, A. (2020, September 16). Some Advances on Bayesian Record Linkage and Inference for Linked Data 2013. Available online: http://www.ine.es/e/essnetdi_ws2011/ppts/Liseo_Tancredi.pdf."
    },
    {
      "key": "ref_25",
      "doi-asserted-by": "crossref",
      "first-page": "1660",
      "DOI": "10.1080/01621459.2015.1105807",
      "article-title": "A Bayesian approach to graphical record linkage and deduplication",
      "volume": "111",
      "author": "Steorts",
      "year": "2016",
      "journal-title": "J. Am. Stat. Assoc."
    },
    {
      "key": "ref_26",
      "doi-asserted-by": "crossref",
      "first-page": "e16757",
      "DOI": "10.2196/16757",
      "article-title": "Privacy-Preserving Record Linkage of Deidentified Records Within a Public Health Surveillance System: Evaluation Study",
      "volume": "22",
      "author": "Nguyen",
      "year": "2020",
      "journal-title": "J. Med. Internet Res."
    },
    {
      "key": "ref_27",
      "doi-asserted-by": "crossref",
      "first-page": "1",
      "DOI": "10.1186/s12874-020-01064-1",
      "article-title": "Sources of potential bias when combining routine data linkage and a national survey of secondary school-aged children: A record linkage study",
      "volume": "20",
      "author": "Morgan",
      "year": "2020",
      "journal-title": "BMC Med Res. Methodol."
    },
    {
      "key": "ref_28",
      "unstructured": "(2019, October 24). Smartystreets. Available online: https://smartystreets.com/pricing."
    },
    {
      "key": "ref_29",
      "doi-asserted-by": "crossref",
      "unstructured": "Harron, K., Goldstein, H., and Dibben, C. (2015). Record linkage: A missing data problem. Methodological Developments in Data Linkage, John Wiley and Sons.",
      "DOI": "10.1002/9781119072454"
    },
    {
      "key": "ref_30",
      "doi-asserted-by": "crossref",
      "first-page": "43",
      "DOI": "10.1016/j.jbi.2014.01.016",
      "article-title": "Improving record linkage performance in the presence of missing linkage data",
      "volume": "52",
      "author": "Ong",
      "year": "2014",
      "journal-title": "J. Biomed. Inf."
    },
    {
      "key": "ref_31",
      "unstructured": "Resnick, D., and Asher, J. (2019, January 1). Measurement of Type I and Type II Record Linkage Error. Proceedings of the American Statistical Association, Government Statistics Section, Denver, CO, USA."
    },
    {
      "key": "ref_32",
      "doi-asserted-by": "crossref",
      "unstructured": "Karr, A.F., Taylor, M.T., West, S.L., Setoguchi, S., Kou, T.D., Gerhard, T., and Horton, D.B. (2019). Comparing record linkage software programs and algorithms using real-world data. PLoS ONE, 14.",
      "DOI": "10.1371/journal.pone.0221459"
    },
    {
      "key": "ref_33",
      "doi-asserted-by": "crossref",
      "first-page": "353",
      "DOI": "10.1017/S0003055418000783",
      "article-title": "Using a probabilistic model to assist merging of large-scale administrative records",
      "volume": "113",
      "author": "Enamorado",
      "year": "2019",
      "journal-title": "Am. Polit. Sci. Rev."
    },
    {
      "key": "ref_34",
      "doi-asserted-by": "crossref",
      "first-page": "946",
      "DOI": "10.1016/j.is.2012.11.005",
      "article-title": "A taxonomy of privacy-preserving record linkage techniques",
      "volume": "38",
      "author": "Vatsalan",
      "year": "2013",
      "journal-title": "Inform. Syst."
    },
    {
      "key": "ref_35",
      "unstructured": "(2020, September 21). Privacy Preserving Record Linkage. Available online: https://github.com/data61/anonlink."
    },
    {
      "key": "ref_36",
      "unstructured": "(2019, December 31). Linkwise: A Modern Privacy Preserving Record Linkage Software. Available online: https://policywise.com/2018/03/15/linkwise/."
    },
    {
      "key": "ref_37",
      "unstructured": "(2019, December 31). PPRL: Privacy Preserving Record Linkage. Available online: https://cran.r-project.org/web/packages/PPRL/index.html."
    },
    {
      "key": "ref_38",
      "doi-asserted-by": "crossref",
      "first-page": "1263",
      "DOI": "10.1177/0898264311421369",
      "article-title": "Differential record linkage by Hispanic ethnicity and age in linked mortality studies: Implications for the epidemiologic paradox",
      "volume": "23",
      "author": "Lariscy",
      "year": "2011",
      "journal-title": "J. Aging Health"
    },
    {
      "key": "ref_39",
      "doi-asserted-by": "crossref",
      "first-page": "137",
      "DOI": "10.1007/s11113-016-9415-z",
      "article-title": "Black–white disparities in adult mortality: Implications of differential record linkage for understanding the mortality crossover",
      "volume": "36",
      "author": "Lariscy",
      "year": "2017",
      "journal-title": "Popul. Res. Pol. Rev."
    },
    {
      "key": "ref_40",
      "unstructured": "Bhulai, S., and Semanjski, I. (2016). Performance of Spanish Encoding Functions during Record Linkage. Data Analytics 2016, Proceedings of the Fifth International Conference on Data Analytics, Venice, Italy, 9–13 October 2016, IARIA."
    },
    {
      "key": "ref_41",
      "unstructured": "Král, P., and Matoušek, V. (2015, January 14–17). Named entity recognition for Mongolian language. Proceedings of the International Conference on Text, Speech, and Dialogue, Pilsen, Czech Republic."
    },
    {
      "key": "ref_42",
      "doi-asserted-by": "crossref",
      "unstructured": "Ma, B., Yang, Y., Zhou, X., and Wang, L. (2016, January 21–23). Graph-based short text entity linking: A data integration perspective. Proceedings of the 2016 International Conference on Asian Language Processing (IALP), Tainan, Taiwan.",
      "DOI": "10.1109/IALP.2016.7875966"
    }
  ],
  "container-title": [
    "International Journal of Environmental Research and Public Health"
  ],
  "original-title": [],
  "language": "en",
  "link": [
    {
      "URL": "https://www.mdpi.com/1660-4601/17/18/6937/pdf",
      "content-type": "unspecified",
      "content-version": "vor",
      "intended-application": "similarity-checking"
    }
  ],
  "deposited": {
    "date-parts": [
      [
        2025,
        10,
        11
      ]
    ],
    "date-time": "2025-10-11T10:12:36Z",
    "timestamp": 1760177556000
  },
  "score": 1,
  "resource": {
    "primary": {
      "URL": "https://www.mdpi.com/1660-4601/17/18/6937"
    }
  },
  "subtitle": [],
  "short-title": [],
  "issued": {
    "date-parts": [
      [
        2020,
        9,
        22
      ]
    ]
  },
  "references-count": 42,
  "journal-issue": {
    "issue": "18",
    "published-online": {
      "date-parts": [
        [
          2020,
          9
        ]
      ]
    }
  },
  "alternative-id": [
    "ijerph17186937"
  ],
  "URL": "https://doi.org/10.3390/ijerph17186937",
  "relation": {},
  "ISSN": [
    "1660-4601"
  ],
  "issn-type": [
    {
      "value": "1660-4601",
      "type": "electronic"
    }
  ],
  "subject": [],
  "published": {
    "date-parts": [
      [
        2020,
        9,
        22
      ]
    ]
  }
}