[
  {
    "id": "https://openalex.org/W2926563150",
    "doi": "https://doi.org/10.29397/reciis.v13i1.1469",
    "title": "Tecnologias digitais de informação para a saúde: revisando os padrões de metadados com foco na interoperabilidade",
    "display_name": "Tecnologias digitais de informação para a saúde: revisando os padrões de metadados com foco na interoperabilidade",
    "relevance_score": 160.39537,
    "publication_year": 2019,
    "publication_date": "2019-03-29",
    "ids": {
      "openalex": "https://openalex.org/W2926563150",
      "doi": "https://doi.org/10.29397/reciis.v13i1.1469",
      "mag": "2926563150"
    },
    "language": "pt",
    "primary_location": {
      "id": "doi:10.29397/reciis.v13i1.1469",
      "is_oa": true,
      "landing_page_url": "https://doi.org/10.29397/reciis.v13i1.1469",
      "pdf_url": "https://www.reciis.icict.fiocruz.br/index.php/reciis/article/download/1469/2264",
      "source": {
        "id": "https://openalex.org/S30403921",
        "display_name": "Reciis",
        "issn_l": "1981-6278",
        "issn": [
          "1981-6278",
          "1981-6286"
        ],
        "is_oa": true,
        "is_in_doaj": true,
        "is_core": false,
        "host_organization": "https://openalex.org/P4310312271",
        "host_organization_name": "Instituto de Comunicação e Informação Científica e Tecnológica em Saúde (Icict) da Fundação Oswaldo Cruz (Fiocruz)",
        "host_organization_lineage": [
          "https://openalex.org/P4310312271"
        ],
        "host_organization_lineage_names": [
          "Instituto de Comunicação e Informação Científica e Tecnológica em Saúde (Icict) da Fundação Oswaldo Cruz (Fiocruz)"
        ],
        "type": "journal"
      },
      "license": "cc-by-nc",
      "license_id": "https://openalex.org/licenses/cc-by-nc",
      "version": "publishedVersion",
      "is_accepted": true,
      "is_published": true,
      "raw_source_name": "Revista Eletrônica de Comunicação, Informação e Inovação em Saúde",
      "raw_type": "journal-article"
    },
    "type": "article",
    "indexed_in": [
      "crossref",
      "doaj"
    ],
    "open_access": {
      "is_oa": true,
      "oa_status": "diamond",
      "oa_url": "https://www.reciis.icict.fiocruz.br/index.php/reciis/article/download/1469/2264",
      "any_repository_has_fulltext": true
    },
    "authorships": [
      {
        "author_position": "first",
        "author": {
          "id": "https://openalex.org/A5074973151",
          "display_name": "Odete Máyra Mesquita Sales",
          "orcid": "https://orcid.org/0000-0002-9208-3071"
        },
        "institutions": [
          {
            "id": "https://openalex.org/I243754102",
            "display_name": "Universidade Federal do Ceará",
            "ror": "https://ror.org/03srtnf24",
            "country_code": "BR",
            "type": "education",
            "lineage": [
              "https://openalex.org/I243754102"
            ]
          }
        ],
        "countries": [
          "BR"
        ],
        "is_corresponding": true,
        "raw_author_name": "Odete Máyra Mesquita Sales",
        "raw_affiliation_strings": [
          "Universidade Federal do Ceará. Fortaleza, CE"
        ],
        "affiliations": [
          {
            "raw_affiliation_string": "Universidade Federal do Ceará. Fortaleza, CE",
            "institution_ids": [
              "https://openalex.org/I243754102"
            ]
          }
        ]
      },
      {
        "author_position": "last",
        "author": {
          "id": "https://openalex.org/A5011639624",
          "display_name": "Virgínia Bentes Pinto",
          "orcid": "https://orcid.org/0000-0003-1283-8292"
        },
        "institutions": [
          {
            "id": "https://openalex.org/I243754102",
            "display_name": "Universidade Federal do Ceará",
            "ror": "https://ror.org/03srtnf24",
            "country_code": "BR",
            "type": "education",
            "lineage": [
              "https://openalex.org/I243754102"
            ]
          }
        ],
        "countries": [
          "BR"
        ],
        "is_corresponding": false,
        "raw_author_name": "Virginia Bentes Pinto",
        "raw_affiliation_strings": [
          "Universidade Federal do Ceará, CE"
        ],
        "affiliations": [
          {
            "raw_affiliation_string": "Universidade Federal do Ceará, CE",
            "institution_ids": [
              "https://openalex.org/I243754102"
            ]
          }
        ]
      }
    ],
    "institutions": [],
    "countries_distinct_count": 1,
    "institutions_distinct_count": 2,
    "corresponding_author_ids": [
      "https://openalex.org/A5074973151"
    ],
    "corresponding_institution_ids": [
      "https://openalex.org/I243754102"
    ],
    "apc_list": null,
    "apc_paid": null,
    "fwci": 0.72802008,
    "has_fulltext": true,
    "cited_by_count": 11,
    "citation_normalized_percentile": {
      "value": 0.76438943,
      "is_in_top_1_percent": false,
      "is_in_top_10_percent": false
    },
    "cited_by_percentile_year": {
      "min": 89,
      "max": 98
    },
    "biblio": {
      "volume": "13",
      "issue": "1",
      "first_page": null,
      "last_page": null
    },
    "is_retracted": false,
    "is_paratext": false,
    "is_xpac": false,
    "primary_topic": {
      "id": "https://openalex.org/T13166",
      "display_name": "Information Science and Libraries",
      "score": 0.9544000029563904,
      "subfield": {
        "id": "https://openalex.org/subfields/1710",
        "display_name": "Information Systems"
      },
      "field": {
        "id": "https://openalex.org/fields/17",
        "display_name": "Computer Science"
      },
      "domain": {
        "id": "https://openalex.org/domains/3",
        "display_name": "Physical Sciences"
      }
    },
    "topics": [
      {
        "id": "https://openalex.org/T13166",
        "display_name": "Information Science and Libraries",
        "score": 0.9544000029563904,
        "subfield": {
          "id": "https://openalex.org/subfields/1710",
          "display_name": "Information Systems"
        },
        "field": {
          "id": "https://openalex.org/fields/17",
          "display_name": "Computer Science"
        },
        "domain": {
          "id": "https://openalex.org/domains/3",
          "display_name": "Physical Sciences"
        }
      }
    ],
    "keywords": [
      {
        "id": "https://openalex.org/keywords/humanities",
        "display_name": "Humanities",
        "score": 0.6454927325248718
      },
      {
        "id": "https://openalex.org/keywords/political-science",
        "display_name": "Political science",
        "score": 0.4754573702812195
      },
      {
        "id": "https://openalex.org/keywords/geography",
        "display_name": "Geography",
        "score": 0.37116801738739014
      },
      {
        "id": "https://openalex.org/keywords/philosophy",
        "display_name": "Philosophy",
        "score": 0.2530513405799866
      }
    ],
    "concepts": [
      {
        "id": "https://openalex.org/C15708023",
        "wikidata": "https://www.wikidata.org/wiki/Q80083",
        "display_name": "Humanities",
        "level": 1,
        "score": 0.6454927325248718
      },
      {
        "id": "https://openalex.org/C17744445",
        "wikidata": "https://www.wikidata.org/wiki/Q36442",
        "display_name": "Political science",
        "level": 0,
        "score": 0.4754573702812195
      },
      {
        "id": "https://openalex.org/C205649164",
        "wikidata": "https://www.wikidata.org/wiki/Q1071",
        "display_name": "Geography",
        "level": 0,
        "score": 0.37116801738739014
      },
      {
        "id": "https://openalex.org/C138885662",
        "wikidata": "https://www.wikidata.org/wiki/Q5891",
        "display_name": "Philosophy",
        "level": 0,
        "score": 0.2530513405799866
      }
    ],
    "mesh": [],
    "locations_count": 5,
    "locations": [
      {
        "id": "doi:10.29397/reciis.v13i1.1469",
        "is_oa": true,
        "landing_page_url": "https://doi.org/10.29397/reciis.v13i1.1469",
        "pdf_url": "https://www.reciis.icict.fiocruz.br/index.php/reciis/article/download/1469/2264",
        "source": {
          "id": "https://openalex.org/S30403921",
          "display_name": "Reciis",
          "issn_l": "1981-6278",
          "issn": [
            "1981-6278",
            "1981-6286"
          ],
          "is_oa": true,
          "is_in_doaj": true,
          "is_core": false,
          "host_organization": "https://openalex.org/P4310312271",
          "host_organization_name": "Instituto de Comunicação e Informação Científica e Tecnológica em Saúde (Icict) da Fundação Oswaldo Cruz (Fiocruz)",
          "host_organization_lineage": [
            "https://openalex.org/P4310312271"
          ],
          "host_organization_lineage_names": [
            "Instituto de Comunicação e Informação Científica e Tecnológica em Saúde (Icict) da Fundação Oswaldo Cruz (Fiocruz)"
          ],
          "type": "journal"
        },
        "license": "cc-by-nc",
        "license_id": "https://openalex.org/licenses/cc-by-nc",
        "version": "publishedVersion",
        "is_accepted": true,
        "is_published": true,
        "raw_source_name": "Revista Eletrônica de Comunicação, Informação e Inovação em Saúde",
        "raw_type": "journal-article"
      },
      {
        "id": "pmh:oai:americanae.aecid.es:2329099",
        "is_oa": true,
        "landing_page_url": "https://www.arca.fiocruz.br/handle/icict/32635",
        "pdf_url": null,
        "source": {
          "id": "https://openalex.org/S4306400786",
          "display_name": "Americanae (AECID Library)",
          "issn_l": null,
          "issn": null,
          "is_oa": false,
          "is_in_doaj": false,
          "is_core": false,
          "host_organization": null,
          "host_organization_name": null,
          "host_organization_lineage": [],
          "host_organization_lineage_names": [],
          "type": "repository"
        },
        "license": "other-oa",
        "license_id": "https://openalex.org/licenses/other-oa",
        "version": "publishedVersion",
        "is_accepted": true,
        "is_published": true,
        "raw_source_name": "reponame:Repositório Institucional da FIOCRUZ (ARCA)",
        "raw_type": "info:eu-repo/semantics/publishedVersion"
      },
      {
        "id": "pmh:oai:ojs.reciis.icict.fiocruz.br:article/1469",
        "is_oa": true,
        "landing_page_url": "https://www.reciis.icict.fiocruz.br/index.php/reciis/article/view/1469",
        "pdf_url": null,
        "source": null,
        "license": "other-oa",
        "license_id": "https://openalex.org/licenses/other-oa",
        "version": "publishedVersion",
        "is_accepted": true,
        "is_published": true,
        "raw_source_name": "Revista Eletrônica de Comunicação, Informação e Inovação em Saúde; v. 13, n. 1 (2019): Dossiê: Comunicação e riscos em saúde",
        "raw_type": "<dc:type/><dc:type>info:eu-repo/semantics/article"
      },
      {
        "id": "pmh:oai:arca.fiocruz.br:icict/32635",
        "is_oa": true,
        "landing_page_url": "https://arca.fiocruz.br/handle/icict/32635",
        "pdf_url": null,
        "source": null,
        "license": "other-oa",
        "license_id": "https://openalex.org/licenses/other-oa",
        "version": "submittedVersion",
        "is_accepted": false,
        "is_published": false,
        "raw_source_name": "instacron:FIOCRUZ",
        "raw_type": "info:eu-repo/semantics/article"
      },
      {
        "id": "pmh:oai:doaj.org/article:86c8baf336794bd787f18b8ba2f96e9d",
        "is_oa": true,
        "landing_page_url": "https://doaj.org/article/86c8baf336794bd787f18b8ba2f96e9d",
        "pdf_url": null,
        "source": {
          "id": "https://openalex.org/S112646816",
          "display_name": "SHILAP Revista de lepidopterología",
          "issn_l": "0300-5267",
          "issn": [
            "0300-5267",
            "2340-4078"
          ],
          "is_oa": true,
          "is_in_doaj": true,
          "is_core": false,
          "host_organization": null,
          "host_organization_name": null,
          "host_organization_lineage": [],
          "host_organization_lineage_names": [],
          "type": "journal"
        },
        "license": "cc-by-sa",
        "license_id": "https://openalex.org/licenses/cc-by-sa",
        "version": "submittedVersion",
        "is_accepted": false,
        "is_published": false,
        "raw_source_name": "RECIIS, Vol 13, Iss 1 (2019)",
        "raw_type": "article"
      }
    ],
    "best_oa_location": {
      "id": "doi:10.29397/reciis.v13i1.1469",
      "is_oa": true,
      "landing_page_url": "https://doi.org/10.29397/reciis.v13i1.1469",
      "pdf_url": "https://www.reciis.icict.fiocruz.br/index.php/reciis/article/download/1469/2264",
      "source": {
        "id": "https://openalex.org/S30403921",
        "display_name": "Reciis",
        "issn_l": "1981-6278",
        "issn": [
          "1981-6278",
          "1981-6286"
        ],
        "is_oa": true,
        "is_in_doaj": true,
        "is_core": false,
        "host_organization": "https://openalex.org/P4310312271",
        "host_organization_name": "Instituto de Comunicação e Informação Científica e Tecnológica em Saúde (Icict) da Fundação Oswaldo Cruz (Fiocruz)",
        "host_organization_lineage": [
          "https://openalex.org/P4310312271"
        ],
        "host_organization_lineage_names": [
          "Instituto de Comunicação e Informação Científica e Tecnológica em Saúde (Icict) da Fundação Oswaldo Cruz (Fiocruz)"
        ],
        "type": "journal"
      },
      "license": "cc-by-nc",
      "license_id": "https://openalex.org/licenses/cc-by-nc",
      "version": "publishedVersion",
      "is_accepted": true,
      "is_published": true,
      "raw_source_name": "Revista Eletrônica de Comunicação, Informação e Inovação em Saúde",
      "raw_type": "journal-article"
    },
    "sustainable_development_goals": [],
    "awards": [],
    "funders": [],
    "has_content": {
      "pdf": true,
      "grobid_xml": true
    },
    "content_urls": {
      "pdf": "https://content.openalex.org/works/W2926563150.pdf",
      "grobid_xml": "https://content.openalex.org/works/W2926563150.grobid-xml"
    },
    "referenced_works_count": 3,
    "referenced_works": [
      "https://openalex.org/W2016510393",
      "https://openalex.org/W2092909397",
      "https://openalex.org/W2938483208"
    ],
    "related_works": [
      "https://openalex.org/W2748952813",
      "https://openalex.org/W93312527",
      "https://openalex.org/W2603296253",
      "https://openalex.org/W1589203209",
      "https://openalex.org/W2557454913",
      "https://openalex.org/W828925460",
      "https://openalex.org/W11365241",
      "https://openalex.org/W1013667899",
      "https://openalex.org/W2559405764",
      "https://openalex.org/W157591366"
    ],
    "abstract_inverted_index": {
      "Este": [
        0
      ],
      "artigo": [
        1
      ],
      "tem": [
        2
      ],
      "como": [
        3,
        13
      ],
      "objetivo": [
        4
      ],
      "apresentar": [
        5
      ],
      "o": [
        6,
        78,
        124
      ],
      "mapeamento": [
        7
      ],
      "dos": [
        8,
        49
      ],
      "padrões": [
        9,
        50,
        81
      ],
      "de": [
        10,
        21,
        29,
        42,
        51,
        70,
        72,
        74,
        80,
        82,
        86,
        103,
        113,
        116,
        126,
        134
      ],
      "metadados,": [
        11
      ],
      "bem": [
        12
      ],
      "suas": [
        14
      ],
      "aplicações": [
        15
      ],
      "visando": [
        16
      ],
      "à": [
        17
      ],
      "interoperabilidade": [
        18,
        52,
        83,
        100
      ],
      "em": [
        19,
        40,
        88,
        101
      ],
      "sistemas": [
        20,
        85,
        102
      ],
      "informação": [
        22,
        87
      ],
      "para": [
        23,
        84
      ],
      "a": [
        24,
        47,
        97,
        121
      ],
      "área": [
        25
      ],
      "da": [
        26,
        58,
        66
      ],
      "saúde.": [
        27,
        59
      ],
      "Trata-se": [
        28
      ],
      "uma": [
        30
      ],
      "pesquisa": [
        31
      ],
      "exploratório-descritiva": [
        32
      ],
      "com": [
        33
      ],
      "abordagem": [
        34
      ],
      "qualitativa": [
        35
      ],
      "e": [
        36,
        54,
        99,
        123,
        129,
        140
      ],
      "levantamento": [
        37
      ],
      "bibliográfico": [
        38
      ],
      "realizado": [
        39
      ],
      "busca": [
        41
      ],
      "publicações": [
        43
      ],
      "atuais": [
        44
      ],
      "que": [
        45,
        76,
        96
      ],
      "abordam": [
        46
      ],
      "temática": [
        48
      ],
      "nacionais": [
        53
      ],
      "internacionais": [
        55
      ],
      "no": [
        56,
        90
      ],
      "campo": [
        57
      ],
      "Essas": [
        60
      ],
      "buscas": [
        61
      ],
      "foram": [
        62
      ],
      "pautadas": [
        63
      ],
      "nos": [
        64
      ],
      "enunciados": [
        65
      ],
      "Portaria": [
        67
      ],
      "nº": [
        68
      ],
      "2.073,": [
        69
      ],
      "31": [
        71
      ],
      "agosto": [
        73
      ],
      "2011,": [
        75
      ],
      "regulamenta": [
        77
      ],
      "uso": [
        79
      ],
      "saúde": [
        89
      ],
      "contexto": [
        91
      ],
      "brasileiro.": [
        92
      ],
      "Os": [
        93
      ],
      "resultados": [
        94
      ],
      "evidenciam": [
        95
      ],
      "padronização": [
        98
      ],
      "informação,": [
        104
      ],
      "sejam": [
        105
      ],
      "eles": [
        106
      ],
      "relativos": [
        107
      ],
      "às": [
        108,
        111
      ],
      "bibliotecas": [
        109
      ],
      "ou": [
        110
      ],
      "organizações": [
        112
      ],
      "saúde,": [
        114
      ],
      "são": [
        115
      ],
      "extrema": [
        117
      ],
      "importância": [
        118
      ],
      "por": [
        119
      ],
      "possibilitar": [
        120
      ],
      "troca": [
        122
      ],
      "compartilhamento": [
        125
      ],
      "informações": [
        127
      ],
      "dentro": [
        128
      ],
      "fora": [
        130
      ],
      "das": [
        131
      ],
      "organizações,": [
        132
      ],
      "além": [
        133
      ],
      "tornar": [
        135
      ],
      "mais": [
        136
      ],
      "eficientes": [
        137
      ],
      "os": [
        138
      ],
      "fluxos": [
        139
      ],
      "processos": [
        141
      ],
      "informacionais.": [
        142
      ]
    },
    "counts_by_year": [
      {
        "year": 2025,
        "cited_by_count": 5
      },
      {
        "year": 2024,
        "cited_by_count": 3
      },
      {
        "year": 2023,
        "cited_by_count": 1
      },
      {
        "year": 2022,
        "cited_by_count": 1
      },
      {
        "year": 2021,
        "cited_by_count": 1
      }
    ],
    "updated_date": "2026-02-05T00:54:17.221276",
    "created_date": "2019-04-11T00:00:00"
  },
  {
    "id": "https://openalex.org/W2883401544",
    "doi": "https://doi.org/10.17696/2318-3691.25.2.2018.1262",
    "title": "Informática em Saúde e a Interoperabilidade nos Sistemas Hospitalares",
    "display_name": "Informática em Saúde e a Interoperabilidade nos Sistemas Hospitalares",
    "relevance_score": 30.85796,
    "publication_year": 2018,
    "publication_date": "2018-07-20",
    "ids": {
      "openalex": "https://openalex.org/W2883401544",
      "doi": "https://doi.org/10.17696/2318-3691.25.2.2018.1262",
      "mag": "2883401544"
    },
    "language": "pt",
    "primary_location": {
      "id": "doi:10.17696/2318-3691.25.2.2018.1262",
      "is_oa": true,
      "landing_page_url": "http://doi.org/10.17696/2318-3691.25.2.2018.1262",
      "pdf_url": null,
      "source": {
        "id": "https://openalex.org/S2736693268",
        "display_name": "Arquivos de Ciências da Saúde",
        "issn_l": "1807-1325",
        "issn": [
          "1807-1325",
          "2318-3691"
        ],
        "is_oa": true,
        "is_in_doaj": false,
        "is_core": false,
        "host_organization": "https://openalex.org/P4310312110",
        "host_organization_name": "Faculdade de Medicina de São José do Rio Preto",
        "host_organization_lineage": [
          "https://openalex.org/P4310312110"
        ],
        "host_organization_lineage_names": [
          "Faculdade de Medicina de São José do Rio Preto"
        ],
        "type": "journal"
      },
      "license": null,
      "license_id": null,
      "version": "publishedVersion",
      "is_accepted": true,
      "is_published": true,
      "raw_source_name": "Arquivos de Ciências da Saúde",
      "raw_type": "journal-article"
    },
    "type": "article",
    "indexed_in": [
      "crossref"
    ],
    "open_access": {
      "is_oa": true,
      "oa_status": "diamond",
      "oa_url": "http://doi.org/10.17696/2318-3691.25.2.2018.1262",
      "any_repository_has_fulltext": false
    },
    "authorships": [
      {
        "author_position": "first",
        "author": {
          "id": "https://openalex.org/A5006307729",
          "display_name": "Adí­lia Maria Pires Sciarra",
          "orcid": "https://orcid.org/0000-0002-0364-6726"
        },
        "institutions": [],
        "countries": [],
        "is_corresponding": true,
        "raw_author_name": "Adília Maria Pires Sciarra",
        "raw_affiliation_strings": [],
        "affiliations": []
      },
      {
        "author_position": "last",
        "author": {
          "id": "https://openalex.org/A5045795605",
          "display_name": "João Marcelo Rondina",
          "orcid": "https://orcid.org/0000-0002-9316-8157"
        },
        "institutions": [],
        "countries": [],
        "is_corresponding": false,
        "raw_author_name": "João Marcelo Rondina",
        "raw_affiliation_strings": [],
        "affiliations": []
      }
    ],
    "institutions": [],
    "countries_distinct_count": 0,
    "institutions_distinct_count": 2,
    "corresponding_author_ids": [
      "https://openalex.org/A5006307729"
    ],
    "corresponding_institution_ids": [],
    "apc_list": null,
    "apc_paid": null,
    "fwci": 0.8053104,
    "has_fulltext": false,
    "cited_by_count": 1,
    "citation_normalized_percentile": {
      "value": 0.78011825,
      "is_in_top_1_percent": false,
      "is_in_top_10_percent": false
    },
    "cited_by_percentile_year": {
      "min": 90,
      "max": 94
    },
    "biblio": {
      "volume": "25",
      "issue": "2",
      "first_page": "2",
      "last_page": "2"
    },
    "is_retracted": false,
    "is_paratext": false,
    "is_xpac": false,
    "primary_topic": {
      "id": "https://openalex.org/T13117",
      "display_name": "Health Education and Validation",
      "score": 0.8209999799728394,
      "subfield": {
        "id": "https://openalex.org/subfields/3304",
        "display_name": "Education"
      },
      "field": {
        "id": "https://openalex.org/fields/33",
        "display_name": "Social Sciences"
      },
      "domain": {
        "id": "https://openalex.org/domains/2",
        "display_name": "Social Sciences"
      }
    },
    "topics": [
      {
        "id": "https://openalex.org/T13117",
        "display_name": "Health Education and Validation",
        "score": 0.8209999799728394,
        "subfield": {
          "id": "https://openalex.org/subfields/3304",
          "display_name": "Education"
        },
        "field": {
          "id": "https://openalex.org/fields/33",
          "display_name": "Social Sciences"
        },
        "domain": {
          "id": "https://openalex.org/domains/2",
          "display_name": "Social Sciences"
        }
      },
      {
        "id": "https://openalex.org/T14071",
        "display_name": "Healthcare during COVID-19 Pandemic",
        "score": 0.7002999782562256,
        "subfield": {
          "id": "https://openalex.org/subfields/1710",
          "display_name": "Information Systems"
        },
        "field": {
          "id": "https://openalex.org/fields/17",
          "display_name": "Computer Science"
        },
        "domain": {
          "id": "https://openalex.org/domains/3",
          "display_name": "Physical Sciences"
        }
      }
    ],
    "keywords": [
      {
        "id": "https://openalex.org/keywords/humanities",
        "display_name": "Humanities",
        "score": 0.36216628551483154
      },
      {
        "id": "https://openalex.org/keywords/philosophy",
        "display_name": "Philosophy",
        "score": 0.3538399934768677
      },
      {
        "id": "https://openalex.org/keywords/computer-science",
        "display_name": "Computer science",
        "score": 0.341036856174469
      }
    ],
    "concepts": [
      {
        "id": "https://openalex.org/C15708023",
        "wikidata": "https://www.wikidata.org/wiki/Q80083",
        "display_name": "Humanities",
        "level": 1,
        "score": 0.36216628551483154
      },
      {
        "id": "https://openalex.org/C138885662",
        "wikidata": "https://www.wikidata.org/wiki/Q5891",
        "display_name": "Philosophy",
        "level": 0,
        "score": 0.3538399934768677
      },
      {
        "id": "https://openalex.org/C41008148",
        "wikidata": "https://www.wikidata.org/wiki/Q21198",
        "display_name": "Computer science",
        "level": 0,
        "score": 0.341036856174469
      }
    ],
    "mesh": [],
    "locations_count": 1,
    "locations": [
      {
        "id": "doi:10.17696/2318-3691.25.2.2018.1262",
        "is_oa": true,
        "landing_page_url": "http://doi.org/10.17696/2318-3691.25.2.2018.1262",
        "pdf_url": null,
        "source": {
          "id": "https://openalex.org/S2736693268",
          "display_name": "Arquivos de Ciências da Saúde",
          "issn_l": "1807-1325",
          "issn": [
            "1807-1325",
            "2318-3691"
          ],
          "is_oa": true,
          "is_in_doaj": false,
          "is_core": false,
          "host_organization": "https://openalex.org/P4310312110",
          "host_organization_name": "Faculdade de Medicina de São José do Rio Preto",
          "host_organization_lineage": [
            "https://openalex.org/P4310312110"
          ],
          "host_organization_lineage_names": [
            "Faculdade de Medicina de São José do Rio Preto"
          ],
          "type": "journal"
        },
        "license": null,
        "license_id": null,
        "version": "publishedVersion",
        "is_accepted": true,
        "is_published": true,
        "raw_source_name": "Arquivos de Ciências da Saúde",
        "raw_type": "journal-article"
      }
    ],
    "best_oa_location": {
      "id": "doi:10.17696/2318-3691.25.2.2018.1262",
      "is_oa": true,
      "landing_page_url": "http://doi.org/10.17696/2318-3691.25.2.2018.1262",
      "pdf_url": null,
      "source": {
        "id": "https://openalex.org/S2736693268",
        "display_name": "Arquivos de Ciências da Saúde",
        "issn_l": "1807-1325",
        "issn": [
          "1807-1325",
          "2318-3691"
        ],
        "is_oa": true,
        "is_in_doaj": false,
        "is_core": false,
        "host_organization": "https://openalex.org/P4310312110",
        "host_organization_name": "Faculdade de Medicina de São José do Rio Preto",
        "host_organization_lineage": [
          "https://openalex.org/P4310312110"
        ],
        "host_organization_lineage_names": [
          "Faculdade de Medicina de São José do Rio Preto"
        ],
        "type": "journal"
      },
      "license": null,
      "license_id": null,
      "version": "publishedVersion",
      "is_accepted": true,
      "is_published": true,
      "raw_source_name": "Arquivos de Ciências da Saúde",
      "raw_type": "journal-article"
    },
    "sustainable_development_goals": [],
    "awards": [],
    "funders": [],
    "has_content": {
      "pdf": false,
      "grobid_xml": false
    },
    "content_urls": null,
    "referenced_works_count": 0,
    "referenced_works": [],
    "related_works": [
      "https://openalex.org/W2899084033",
      "https://openalex.org/W2748952813",
      "https://openalex.org/W2390279801",
      "https://openalex.org/W2358668433",
      "https://openalex.org/W2780307509",
      "https://openalex.org/W2609344916",
      "https://openalex.org/W2478882070",
      "https://openalex.org/W59019880",
      "https://openalex.org/W2308060692",
      "https://openalex.org/W4210390885"
    ],
    "abstract_inverted_index": {
      "A": [
        0,
        53,
        69,
        287,
        499
      ],
      "Informática": [
        1,
        5,
        70,
        94
      ],
      "em": [
        2,
        13,
        95,
        98,
        127,
        364,
        367,
        394,
        417,
        423,
        451,
        462,
        577,
        619,
        681,
        694,
        717,
        738
      ],
      "Saúde": [
        3,
        14,
        96
      ],
      "ou": [
        4,
        8
      ],
      "Médica": [
        6,
        71
      ],
      ",": [
        7
      ],
      "ainda,": [
        9
      ],
      "Tecnologia": [
        10,
        234
      ],
      "da": [
        11,
        38,
        93,
        152,
        160,
        192,
        220,
        233,
        235,
        264,
        305,
        335,
        445,
        464,
        679,
        697
      ],
      "Informação": [
        12,
        161,
        236
      ],
      "(em": [
        15
      ],
      "Inglês": [
        16
      ],
      "Medical": [
        17
      ],
      "Informatics)é": [
        18
      ],
      "definida": [
        19
      ],
      "por": [
        20,
        124,
        323,
        398,
        457
      ],
      "Blois": [
        21
      ],
      "e": [
        22,
        36,
        41,
        49,
        80,
        87,
        107,
        116,
        129,
        141,
        162,
        171,
        178,
        194,
        204,
        210,
        271,
        275,
        301,
        342,
        377,
        389,
        397,
        407,
        409,
        429,
        489,
        496,
        516,
        521,
        526,
        538,
        565,
        575,
        615,
        642,
        658,
        667,
        705,
        720,
        735,
        742
      ],
      "Shortliffe": [
        23
      ],
      "(1990)": [
        24
      ],
      "como": [
        25,
        507
      ],
      "“um": [
        26
      ],
      "campo": [
        27,
        74
      ],
      "de": [
        28,
        47,
        51,
        62,
        67,
        89,
        105,
        111,
        133,
        137,
        143,
        174,
        176,
        179,
        181,
        196,
        199,
        217,
        244,
        258,
        266,
        285,
        289,
        294,
        307,
        313,
        321,
        326,
        339,
        347,
        354,
        360,
        382,
        415,
        421,
        431,
        433,
        439,
        448,
        487,
        492,
        504,
        509,
        519,
        523,
        528,
        532,
        540,
        554,
        562,
        572,
        585,
        598,
        609,
        617,
        624,
        629,
        631,
        633,
        639,
        648,
        653,
        676,
        686,
        692,
        699,
        703,
        724
      ],
      "rápido": [
        29
      ],
      "desenvolvimento": [
        30
      ],
      "científico": [
        31,
        75
      ],
      "que": [
        32,
        112,
        134,
        165,
        188,
        545,
        557,
        570,
        603,
        645
      ],
      "lida": [
        33
      ],
      "com": [
        34,
        77,
        412,
        663
      ],
      "armazenamento,recuperação": [
        35
      ],
      "uso": [
        37,
        173,
        232
      ],
      "informação,": [
        39
      ],
      "dados": [
        40,
        203,
        290,
        416,
        449,
        467,
        693
      ],
      "conhecimentos": [
        42
      ],
      "biomédicos": [
        43
      ],
      "para": [
        44,
        64,
        82,
        167,
        208,
        248,
        350,
        402,
        437,
        468,
        472,
        556,
        579,
        602,
        688
      ],
      "a": [
        45,
        65,
        169,
        183,
        292,
        302,
        317,
        352,
        373,
        375,
        387,
        390,
        443,
        469,
        490,
        502,
        607,
        668,
        674,
        684,
        736
      ],
      "resolução": [
        46
      ],
      "problemas": [
        48
      ],
      "tomada": [
        50,
        66,
        142
      ],
      "decisão”.": [
        52
      ],
      "Saúdeé": [
        54
      ],
      "uma": [
        55,
        246,
        250,
        254,
        282,
        552,
        599,
        677
      ],
      "das": [
        56,
        158
      ],
      "áreas": [
        57
      ],
      "onde": [
        58
      ],
      "há": [
        59
      ],
      "maior": [
        60,
        269,
        517
      ],
      "necessidade": [
        61,
        608
      ],
      "informação": [
        63,
        177,
        193,
        680
      ],
      "decisões.": [
        68
      ],
      "é": [
        72,
        549,
        672
      ],
      "o": [
        73,
        84,
        113,
        172,
        230,
        357,
        378,
        484,
        511,
        636,
        690,
        731
      ],
      "quelida": [
        76
      ],
      "recursos,": [
        78
      ],
      "dispositivos": [
        79
      ],
      "métodos": [
        81,
        125
      ],
      "otimizar": [
        83,
        730
      ],
      "armazenamento,": [
        85
      ],
      "recuperação": [
        86
      ],
      "gerenciamento": [
        88
      ],
      "informações": [
        90,
        118,
        505,
        561,
        584,
        614,
        649
      ],
      "biomédicas.O": [
        91
      ],
      "crescimento": [
        92
      ],
      "deve-se,": [
        97
      ],
      "grande": [
        99
      ],
      "parte:": [
        100
      ],
      "aos": [
        101,
        380
      ],
      "avanços": [
        102
      ],
      "nas": [
        103
      ],
      "tecnologias": [
        104,
        544
      ],
      "computação": [
        106
      ],
      "comunicação,": [
        108
      ],
      "àcrescente": [
        109
      ],
      "convicção": [
        110
      ],
      "conhecimento": [
        114,
        140,
        180,
        327
      ],
      "médico": [
        115
      ],
      "as": [
        117,
        155,
        332,
        613
      ],
      "sobre": [
        119
      ],
      "os": [
        120,
        135,
        189,
        213,
        592,
        651,
        664
      ],
      "pacientes": [
        121
      ],
      "são": [
        122,
        635
      ],
      "ingerenciáveis": [
        123
      ],
      "tradicionaisbaseados": [
        126
      ],
      "papel,": [
        128
      ],
      "devido": [
        130
      ],
      "à": [
        131,
        710
      ],
      "certeza": [
        132
      ],
      "processos": [
        136
      ],
      "acesso": [
        138,
        379,
        582
      ],
      "ao": [
        139,
        280,
        713,
        722,
        733
      ],
      "decisão": [
        144
      ],
      "desempenham": [
        145
      ],
      "papelcentral": [
        146
      ],
      "na": [
        147,
        708
      ],
      "Medicina": [
        148
      ],
      "moderna.Portanto,": [
        149
      ],
      "no": [
        150,
        222,
        514
      ],
      "setor": [
        151,
        219
      ],
      "saúde,": [
        153,
        695,
        739
      ],
      "dentre": [
        154
      ],
      "diversas": [
        156,
        536
      ],
      "aplicações": [
        157
      ],
      "Tecnologias": [
        159
      ],
      "Comunicação": [
        163
      ],
      "(TIC)": [
        164
      ],
      "desempenhamrecursos": [
        166
      ],
      "facilitar": [
        168
      ],
      "criação": [
        170
      ],
      "dados,": [
        175
      ],
      "saúde;": [
        182
      ],
      "Interoperabilidade": [
        184,
        240,
        318,
        336,
        618,
        625
      ],
      "surge": [
        185
      ],
      "comoa": [
        186
      ],
      "capacidade": [
        187,
        401
      ],
      "diversos": [
        190,
        418
      ],
      "sistemas": [
        191,
        320,
        338,
        424,
        652
      ],
      "aplicativos": [
        195
      ],
      "software": [
        197
      ],
      "têm": [
        198
      ],
      "se": [
        200
      ],
      "comunicar,": [
        201
      ],
      "trocar": [
        202
      ],
      "utilizar": [
        205
      ],
      "asinformações": [
        206
      ],
      "trocadas": [
        207
      ],
      "suportar": [
        209
      ],
      "viabilizar": [
        211
      ],
      "todos": [
        212,
        558,
        591,
        700
      ],
      "aspectos": [
        214
      ],
      "do": [
        215,
        252,
        273,
        277,
        328,
        344,
        459,
        715
      ],
      "sistema": [
        216,
        453,
        574
      ],
      "saúde.O": [
        218
      ],
      "saúde": [
        221,
        314,
        322,
        348,
        353,
        361,
        541,
        620,
        654,
        704,
        711
      ],
      "Brasil": [
        223,
        612
      ],
      "ainda": [
        224,
        410
      ],
      "guarda": [
        225
      ],
      "muitos": [
        226
      ],
      "desafios,": [
        227
      ],
      "entre": [
        228,
        534,
        605,
        650
      ],
      "eles": [
        229
      ],
      "próprio": [
        231
      ],
      "(TI).": [
        237
      ],
      "Nesse": [
        238
      ],
      "aspecto,a": [
        239
      ],
      "já": [
        241,
        542
      ],
      "está": [
        242
      ],
      "deixando": [
        243
      ],
      "ser": [
        245,
        249,
        297
      ],
      "tendência": [
        247
      ],
      "exigência": [
        251
      ],
      "mercado,": [
        253
      ],
      "vez": [
        255
      ],
      "que,": [
        256,
        473
      ],
      "além": [
        257,
        696
      ],
      "reduzir": [
        259
      ],
      "custose": [
        260
      ],
      "eliminar": [
        261
      ],
      "deficiências": [
        262
      ],
      "através": [
        263,
        597
      ],
      "automatização": [
        265
      ],
      "tarefas,": [
        267
      ],
      "oferece": [
        268
      ],
      "controle": [
        270,
        485,
        518
      ],
      "agilidade": [
        272
      ],
      "workflow": [
        274
      ],
      "otimização": [
        276
      ],
      "tempo;garante": [
        278
      ],
      "também": [
        279
      ],
      "paciente": [
        281,
        734
      ],
      "melhor": [
        283
      ],
      "experiência": [
        284
      ],
      "atendimento.": [
        286
      ],
      "análise": [
        288,
        503
      ],
      "facilita": [
        291,
        369
      ],
      "identificação": [
        293
      ],
      "pontos": [
        295
      ],
      "quedevem": [
        296
      ],
      "mais": [
        298
      ],
      "bem": [
        299
      ],
      "trabalhados": [
        300
      ],
      "realocação": [
        303
      ],
      "estratégica": [
        304
      ],
      "força": [
        306
      ],
      "trabalho.": [
        308
      ],
      "No": [
        309
      ],
      "entanto,": [
        310
      ],
      "muitas": [
        311
      ],
      "organizações": [
        312,
        537
      ],
      "aindanão": [
        315
      ],
      "adotaram": [
        316
      ],
      "dos": [
        319
      ],
      "mera": [
        324
      ],
      "falta": [
        325,
        491
      ],
      "processo.": [
        329
      ],
      "São": [
        330
      ],
      "três": [
        331
      ],
      "etapas": [
        333
      ],
      "paraimplementação": [
        334
      ],
      "nos": [
        337
      ],
      "saúde:1.": [
        340
      ],
      "Desenvolvimento": [
        341,
        428
      ],
      "implementação": [
        343,
        430
      ],
      "registro": [
        345,
        358
      ],
      "eletrônico": [
        346,
        359
      ],
      "(EHR):Essencial": [
        349
      ],
      "trabalhar": [
        351
      ],
      "forma": [
        355,
        563,
        727
      ],
      "preventiva,": [
        356
      ],
      "(ou": [
        362
      ],
      "EHR,": [
        363
      ],
      "sua": [
        365
      ],
      "sigla": [
        366
      ],
      "inglês),": [
        368
      ],
      "acontinuidade,": [
        370
      ],
      "e,": [
        371
      ],
      "portanto": [
        372
      ],
      "qualidade,": [
        374
      ],
      "eficiência": [
        376
      ],
      "cuidados": [
        381
      ],
      "saúde.": [
        383
      ],
      "O": [
        384,
        670
      ],
      "EHR": [
        385
      ],
      "garante": [
        386
      ],
      "integridade": [
        388
      ],
      "permanência": [
        391
      ],
      "dainformação": [
        392
      ],
      "original": [
        393
      ],
      "formato": [
        395
      ],
      "acordado": [
        396
      ],
      "tempo": [
        399,
        460,
        512
      ],
      "determinado;": [
        400
      ],
      "diferentes": [
        403,
        413
      ],
      "vistas": [
        404
      ],
      "pelos": [
        405
      ],
      "utilizadores,": [
        406
      ],
      "interaçõesamigáveis": [
        408
      ],
      "interoperação": [
        411
      ],
      "bases": [
        414
      ],
      "locais": [
        419
      ],
      "(capacidade": [
        420
      ],
      "integração": [
        422
      ],
      "clínicose": [
        425
      ],
      "administrativos": [
        426
      ],
      "diferentes).2.": [
        427
      ],
      "medidas": [
        432
      ],
      "desempenho": [
        434
      ],
      "administrativo": [
        435
      ],
      "sensíveis": [
        436
      ],
      "certificação:Além": [
        438
      ],
      "grandes": [
        440
      ],
      "custos": [
        441
      ],
      "operacionais,": [
        442
      ],
      "desorganização": [
        444
      ],
      "imensa": [
        446
      ],
      "quantidade": [
        447
      ],
      "coletados": [
        450
      ],
      "um": [
        452,
        529,
        573,
        586
      ],
      "hospitalargera": [
        454
      ],
      "déficit": [
        455
      ],
      "indireto": [
        456
      ],
      "conta": [
        458
      ],
      "perdido": [
        461
      ],
      "busca": [
        463
      ],
      "tradução": [
        465
      ],
      "desses": [
        466
      ],
      "mesma": [
        470
      ],
      "linguagem,": [
        471
      ],
      "só": [
        474
      ],
      "então,os": [
        475
      ],
      "profissionais": [
        476
      ],
      "possam": [
        477
      ],
      "atender": [
        478
      ],
      "seus": [
        479
      ],
      "pacientes.": [
        480
      ],
      "Por": [
        481
      ],
      "outro": [
        482,
        578
      ],
      "lado,": [
        483
      ],
      "ineficiente": [
        486
      ],
      "fornecedores": [
        488
      ],
      "transparênciageram": [
        493
      ],
      "gastos": [
        494
      ],
      "desnecessários": [
        495
      ],
      "vultosos": [
        497
      ],
      "anualmente.": [
        498
      ],
      "interoperabilidade": [
        500
      ],
      "viabiliza": [
        501
      ],
      "estratégicas,": [
        506
      ],
      "oaproveitamento": [
        508
      ],
      "leitos,": [
        510
      ],
      "gasto": [
        513
      ],
      "atendimento": [
        515,
        732
      ],
      "estoques": [
        520
      ],
      "pagamento": [
        522
      ],
      "fornecedores:3.": [
        524
      ],
      "Definição": [
        525
      ],
      "adoção": [
        527
      ],
      "padrão": [
        530
      ],
      "único": [
        531
      ],
      "linguagem": [
        533,
        555
      ],
      "sistemas:Hoje": [
        535
      ],
      "instituições": [
        539
      ],
      "utilizam": [
        543
      ],
      "digitalizam": [
        546
      ],
      "processos,": [
        547
      ],
      "mas": [
        548
      ],
      "necessário": [
        550
      ],
      "quehaja": [
        551
      ],
      "padronização": [
        553
      ],
      "consigam": [
        559
      ],
      "intercambiar": [
        560
      ],
      "eficiente": [
        564
      ],
      "rápida.": [
        566
      ],
      "Hoje,": [
        567
      ],
      "ummédico": [
        568
      ],
      "tem": [
        569
      ],
      "sair": [
        571
      ],
      "entrar": [
        576
      ],
      "poder": [
        580
      ],
      "ter": [
        581
      ],
      "às": [
        583
      ],
      "mesmo": [
        587
      ],
      "paciente.": [
        588
      ],
      "Para": [
        589
      ],
      "haverinteroperabilidade,": [
        590
      ],
      "players": [
        593
      ],
      "precisam": [
        594
      ],
      "estar": [
        595
      ],
      "integrados": [
        596
      ],
      "única": [
        600
      ],
      "linguagem-padrão,": [
        601
      ],
      "conversem": [
        604
      ],
      "sisem": [
        606
      ],
      "intervenção": [
        610
      ],
      "humana.No": [
        611
      ],
      "padrões": [
        616
      ],
      "disponibilizados": [
        621
      ],
      "pelo": [
        622
      ],
      "projeto": [
        623
      ],
      "SOA-SUS(portaria": [
        626
      ],
      "nº": [
        627
      ],
      "2.073,": [
        628
      ],
      "31": [
        630
      ],
      "agosto": [
        632
      ],
      "2011)": [
        634
      ],
      "conjunto": [
        637
      ],
      "mínimo": [
        638
      ],
      "premissas,": [
        640
      ],
      "políticas": [
        641
      ],
      "especificações": [
        643
      ],
      "técnicas": [
        644
      ],
      "disciplinamo": [
        646
      ],
      "intercâmbio": [
        647
      ],
      "Federal,": [
        655
      ],
      "Municipal,": [
        656
      ],
      "Distrital": [
        657
      ],
      "Estadual,": [
        659
      ],
      "estabelecendo": [
        660
      ],
      "condições": [
        661
      ],
      "deinteração": [
        662
      ],
      "entes": [
        665
      ],
      "federativos": [
        666
      ],
      "sociedade.": [
        669
      ],
      "objetivo": [
        671
      ],
      "promover": [
        673
      ],
      "utilização": [
        675
      ],
      "arquitetura": [
        678
      ],
      "saúdeque": [
        682
      ],
      "contemple": [
        683
      ],
      "representação": [
        685
      ],
      "conceitos": [
        687
      ],
      "permitir": [
        689
      ],
      "compartilhamento": [
        691
      ],
      "cooperação": [
        698
      ],
      "osprofissionais,": [
        701
      ],
      "estabelecimentos": [
        702
      ],
      "demais": [
        706
      ],
      "envolvidos": [
        707
      ],
      "atenção": [
        709
      ],
      "prestada": [
        712
      ],
      "usuário": [
        714
      ],
      "SUS,": [
        716
      ],
      "meio": [
        718
      ],
      "seguro": [
        719
      ],
      "comrespeito": [
        721
      ],
      "direito": [
        723
      ],
      "privacidade.": [
        725
      ],
      "Dessa": [
        726
      ],
      "será": [
        728
      ],
      "possível": [
        729
      ],
      "gestão": [
        737
      ],
      "reduzindocustos,": [
        740
      ],
      "retrabalhos": [
        741
      ],
      "erros": [
        743
      ],
      "humanos.": [
        744
      ]
    },
    "counts_by_year": [
      {
        "year": 2019,
        "cited_by_count": 1
      }
    ],
    "updated_date": "2025-11-06T03:46:38.306776",
    "created_date": "2025-10-10T00:00:00"
  }
]