[
  {
    "id": "https://openalex.org/W2003304065",
    "doi": "https://doi.org/10.1590/s1415-790x2002000200006",
    "title": "Avaliação de diferentes estratégias de blocagem no relacionamento probabilístico de registros",
    "display_name": "Avaliação de diferentes estratégias de blocagem no relacionamento probabilístico de registros",
    "relevance_score": 3243.3032,
    "publication_year": 2002,
    "publication_date": "2002-08-01",
    "ids": {
      "openalex": "https://openalex.org/W2003304065",
      "doi": "https://doi.org/10.1590/s1415-790x2002000200006",
      "mag": "2003304065"
    },
    "language": "pt",
    "primary_location": {
      "id": "doi:10.1590/s1415-790x2002000200006",
      "is_oa": true,
      "landing_page_url": "https://doi.org/10.1590/s1415-790x2002000200006",
      "pdf_url": "https://www.scielo.br/j/rbepid/a/fQyvCyD5JBhjJqL4bptp9Zs/?lang=pt&format=pdf",
      "source": {
        "id": "https://openalex.org/S142561611",
        "display_name": "Revista Brasileira de Epidemiologia",
        "issn_l": "1415-790X",
        "issn": [
          "1415-790X",
          "1980-5497"
        ],
        "is_oa": true,
        "is_in_doaj": true,
        "is_core": false,
        "host_organization": "https://openalex.org/P4310312543",
        "host_organization_name": "Associação Brasileira de Saúde Coletiva",
        "host_organization_lineage": [
          "https://openalex.org/P4310312543"
        ],
        "host_organization_lineage_names": [
          "Associação Brasileira de Saúde Coletiva"
        ],
        "type": "journal"
      },
      "license": "cc-by-nc",
      "license_id": "https://openalex.org/licenses/cc-by-nc",
      "version": "publishedVersion",
      "is_accepted": true,
      "is_published": true,
      "raw_source_name": "Revista Brasileira de Epidemiologia",
      "raw_type": "journal-article"
    },
    "type": "article",
    "indexed_in": [
      "crossref",
      "doaj"
    ],
    "open_access": {
      "is_oa": true,
      "oa_status": "diamond",
      "oa_url": "https://www.scielo.br/j/rbepid/a/fQyvCyD5JBhjJqL4bptp9Zs/?lang=pt&format=pdf",
      "any_repository_has_fulltext": true
    },
    "authorships": [
      {
        "author_position": "first",
        "author": {
          "id": "https://openalex.org/A5079601916",
          "display_name": "Cláudia Medina Coeli",
          "orcid": "https://orcid.org/0000-0003-1757-3940"
        },
        "institutions": [
          {
            "id": "https://openalex.org/I122140584",
            "display_name": "Universidade Federal do Rio de Janeiro",
            "ror": "https://ror.org/03490as77",
            "country_code": "BR",
            "type": "education",
            "lineage": [
              "https://openalex.org/I122140584"
            ]
          }
        ],
        "countries": [
          "BR"
        ],
        "is_corresponding": true,
        "raw_author_name": "Cláudia Medina Coeli",
        "raw_affiliation_strings": [
          "Universidade Federal do Rio de Janeiro"
        ],
        "affiliations": [
          {
            "raw_affiliation_string": "Universidade Federal do Rio de Janeiro",
            "institution_ids": [
              "https://openalex.org/I122140584"
            ]
          }
        ]
      },
      {
        "author_position": "last",
        "author": {
          "id": "https://openalex.org/A5051988981",
          "display_name": "Kenneth Rochel de Camargo",
          "orcid": "https://orcid.org/0000-0003-3606-5853"
        },
        "institutions": [
          {
            "id": "https://openalex.org/I122140584",
            "display_name": "Universidade Federal do Rio de Janeiro",
            "ror": "https://ror.org/03490as77",
            "country_code": "BR",
            "type": "education",
            "lineage": [
              "https://openalex.org/I122140584"
            ]
          }
        ],
        "countries": [
          "BR"
        ],
        "is_corresponding": false,
        "raw_author_name": "Kenneth Rochel de Camargo Jr.",
        "raw_affiliation_strings": [
          "Universidade Federal do Rio de Janeiro"
        ],
        "affiliations": [
          {
            "raw_affiliation_string": "Universidade Federal do Rio de Janeiro",
            "institution_ids": [
              "https://openalex.org/I122140584"
            ]
          }
        ]
      }
    ],
    "institutions": [],
    "countries_distinct_count": 1,
    "institutions_distinct_count": 2,
    "corresponding_author_ids": [
      "https://openalex.org/A5079601916"
    ],
    "corresponding_institution_ids": [
      "https://openalex.org/I122140584"
    ],
    "apc_list": null,
    "apc_paid": null,
    "fwci": 0.0,
    "has_fulltext": true,
    "cited_by_count": 66,
    "citation_normalized_percentile": {
      "value": 0.16209908,
      "is_in_top_1_percent": false,
      "is_in_top_10_percent": false
    },
    "cited_by_percentile_year": {
      "min": 89,
      "max": 99
    },
    "biblio": {
      "volume": "5",
      "issue": "2",
      "first_page": "185",
      "last_page": "196"
    },
    "is_retracted": false,
    "is_paratext": false,
    "is_xpac": false,
    "primary_topic": {
      "id": "https://openalex.org/T11719",
      "display_name": "Data Quality and Management",
      "score": 0.9994000196456909,
      "subfield": {
        "id": "https://openalex.org/subfields/1803",
        "display_name": "Management Science and Operations Research"
      },
      "field": {
        "id": "https://openalex.org/fields/18",
        "display_name": "Decision Sciences"
      },
      "domain": {
        "id": "https://openalex.org/domains/2",
        "display_name": "Social Sciences"
      }
    },
    "topics": [
      {
        "id": "https://openalex.org/T11719",
        "display_name": "Data Quality and Management",
        "score": 0.9994000196456909,
        "subfield": {
          "id": "https://openalex.org/subfields/1803",
          "display_name": "Management Science and Operations Research"
        },
        "field": {
          "id": "https://openalex.org/fields/18",
          "display_name": "Decision Sciences"
        },
        "domain": {
          "id": "https://openalex.org/domains/2",
          "display_name": "Social Sciences"
        }
      },
      {
        "id": "https://openalex.org/T12741",
        "display_name": "Maternal and Neonatal Healthcare",
        "score": 0.9477999806404114,
        "subfield": {
          "id": "https://openalex.org/subfields/3600",
          "display_name": "General Health Professions"
        },
        "field": {
          "id": "https://openalex.org/fields/36",
          "display_name": "Health Professions"
        },
        "domain": {
          "id": "https://openalex.org/domains/4",
          "display_name": "Health Sciences"
        }
      }
    ],
    "keywords": [
      {
        "id": "https://openalex.org/keywords/humanities",
        "display_name": "Humanities",
        "score": 0.3915024995803833
      },
      {
        "id": "https://openalex.org/keywords/philosophy",
        "display_name": "Philosophy",
        "score": 0.1535407304763794
      }
    ],
    "concepts": [
      {
        "id": "https://openalex.org/C15708023",
        "wikidata": "https://www.wikidata.org/wiki/Q80083",
        "display_name": "Humanities",
        "level": 1,
        "score": 0.3915024995803833
      },
      {
        "id": "https://openalex.org/C138885662",
        "wikidata": "https://www.wikidata.org/wiki/Q5891",
        "display_name": "Philosophy",
        "level": 0,
        "score": 0.1535407304763794
      }
    ],
    "mesh": [],
    "locations_count": 2,
    "locations": [
      {
        "id": "doi:10.1590/s1415-790x2002000200006",
        "is_oa": true,
        "landing_page_url": "https://doi.org/10.1590/s1415-790x2002000200006",
        "pdf_url": "https://www.scielo.br/j/rbepid/a/fQyvCyD5JBhjJqL4bptp9Zs/?lang=pt&format=pdf",
        "source": {
          "id": "https://openalex.org/S142561611",
          "display_name": "Revista Brasileira de Epidemiologia",
          "issn_l": "1415-790X",
          "issn": [
            "1415-790X",
            "1980-5497"
          ],
          "is_oa": true,
          "is_in_doaj": true,
          "is_core": false,
          "host_organization": "https://openalex.org/P4310312543",
          "host_organization_name": "Associação Brasileira de Saúde Coletiva",
          "host_organization_lineage": [
            "https://openalex.org/P4310312543"
          ],
          "host_organization_lineage_names": [
            "Associação Brasileira de Saúde Coletiva"
          ],
          "type": "journal"
        },
        "license": "cc-by-nc",
        "license_id": "https://openalex.org/licenses/cc-by-nc",
        "version": "publishedVersion",
        "is_accepted": true,
        "is_published": true,
        "raw_source_name": "Revista Brasileira de Epidemiologia",
        "raw_type": "journal-article"
      },
      {
        "id": "pmh:oai:doaj.org/article:d806977c4e1647ccad95dabd44ecdf7b",
        "is_oa": true,
        "landing_page_url": "https://doaj.org/article/d806977c4e1647ccad95dabd44ecdf7b",
        "pdf_url": null,
        "source": {
          "id": "https://openalex.org/S112646816",
          "display_name": "SHILAP Revista de lepidopterología",
          "issn_l": "0300-5267",
          "issn": [
            "0300-5267",
            "2340-4078"
          ],
          "is_oa": true,
          "is_in_doaj": true,
          "is_core": false,
          "host_organization": null,
          "host_organization_name": null,
          "host_organization_lineage": [],
          "host_organization_lineage_names": [],
          "type": "journal"
        },
        "license": "cc-by-sa",
        "license_id": "https://openalex.org/licenses/cc-by-sa",
        "version": "submittedVersion",
        "is_accepted": false,
        "is_published": false,
        "raw_source_name": "Revista Brasileira de Epidemiologia, Vol 5, Iss 2, Pp 185-196 (2002)",
        "raw_type": "article"
      }
    ],
    "best_oa_location": {
      "id": "doi:10.1590/s1415-790x2002000200006",
      "is_oa": true,
      "landing_page_url": "https://doi.org/10.1590/s1415-790x2002000200006",
      "pdf_url": "https://www.scielo.br/j/rbepid/a/fQyvCyD5JBhjJqL4bptp9Zs/?lang=pt&format=pdf",
      "source": {
        "id": "https://openalex.org/S142561611",
        "display_name": "Revista Brasileira de Epidemiologia",
        "issn_l": "1415-790X",
        "issn": [
          "1415-790X",
          "1980-5497"
        ],
        "is_oa": true,
        "is_in_doaj": true,
        "is_core": false,
        "host_organization": "https://openalex.org/P4310312543",
        "host_organization_name": "Associação Brasileira de Saúde Coletiva",
        "host_organization_lineage": [
          "https://openalex.org/P4310312543"
        ],
        "host_organization_lineage_names": [
          "Associação Brasileira de Saúde Coletiva"
        ],
        "type": "journal"
      },
      "license": "cc-by-nc",
      "license_id": "https://openalex.org/licenses/cc-by-nc",
      "version": "publishedVersion",
      "is_accepted": true,
      "is_published": true,
      "raw_source_name": "Revista Brasileira de Epidemiologia",
      "raw_type": "journal-article"
    },
    "sustainable_development_goals": [
      {
        "score": 0.4300000071525574,
        "id": "https://metadata.un.org/sdg/3",
        "display_name": "Good health and well-being"
      }
    ],
    "awards": [],
    "funders": [],
    "has_content": {
      "pdf": true,
      "grobid_xml": true
    },
    "content_urls": {
      "pdf": "https://content.openalex.org/works/W2003304065.pdf",
      "grobid_xml": "https://content.openalex.org/works/W2003304065.grobid-xml"
    },
    "referenced_works_count": 16,
    "referenced_works": [
      "https://openalex.org/W1943251102",
      "https://openalex.org/W1980946892",
      "https://openalex.org/W1997321932",
      "https://openalex.org/W2011053338",
      "https://openalex.org/W2034190452",
      "https://openalex.org/W2052390074",
      "https://openalex.org/W2054638248",
      "https://openalex.org/W2073471108",
      "https://openalex.org/W2114973624",
      "https://openalex.org/W2125262832",
      "https://openalex.org/W2128600649",
      "https://openalex.org/W2151870742",
      "https://openalex.org/W2158016453",
      "https://openalex.org/W2810275350",
      "https://openalex.org/W2913519381",
      "https://openalex.org/W3027113960"
    ],
    "related_works": [
      "https://openalex.org/W93312527",
      "https://openalex.org/W2603296253",
      "https://openalex.org/W1589203209",
      "https://openalex.org/W2557454913",
      "https://openalex.org/W828925460",
      "https://openalex.org/W11365241",
      "https://openalex.org/W1013667899",
      "https://openalex.org/W2559405764",
      "https://openalex.org/W157591366",
      "https://openalex.org/W2732870254"
    ],
    "abstract_inverted_index": {
      "A": [
        0,
        126,
        196
      ],
      "blocagem": [
        1,
        45,
        109,
        129
      ],
      "(blocking),": [
        2
      ],
      "que": [
        3,
        22,
        60,
        97,
        153,
        174,
        202
      ],
      "consiste": [
        4
      ],
      "na": [
        5,
        102,
        226
      ],
      "criação": [
        6
      ],
      "de": [
        7,
        10,
        13,
        28,
        31,
        41,
        44,
        52,
        55,
        69,
        78,
        81,
        83,
        91,
        104,
        108,
        122,
        128,
        139,
        147,
        151,
        162,
        169,
        200,
        211,
        230
      ],
      "blocos": [
        8
      ],
      "lógicos": [
        9
      ],
      "registros": [
        11
      ],
      "dentro": [
        12
      ],
      "arquivos": [
        14
      ],
      "a": [
        15,
        39,
        48,
        62,
        120,
        137,
        145,
        173,
        204
      ],
      "serem": [
        16
      ],
      "relacionados,": [
        17
      ],
      "é": [
        18
      ],
      "um": [
        19,
        99,
        148,
        219
      ],
      "dos": [
        20
      ],
      "processos": [
        21
      ],
      "faz": [
        23
      ],
      "parte": [
        24
      ],
      "do": [
        25,
        184,
        187
      ],
      "relacionamento": [
        26,
        77
      ],
      "probabilístico": [
        27
      ],
      "grandes": [
        29
      ],
      "bases": [
        30
      ],
      "dados.": [
        32
      ],
      "Os": [
        33
      ],
      "objetivos": [
        34
      ],
      "deste": [
        35
      ],
      "trabalho": [
        36
      ],
      "são": [
        37
      ],
      "comparar": [
        38
      ],
      "eficiência": [
        40,
        49
      ],
      "diferentes": [
        42,
        161
      ],
      "esquemas": [
        43
      ],
      "e": [
        46,
        119,
        190
      ],
      "estudar": [
        47
      ],
      "da": [
        50,
        179,
        198,
        228
      ],
      "utilização": [
        51,
        197
      ],
      "uma": [
        53,
        79,
        89
      ],
      "rotina": [
        54,
        199
      ],
      "padronização": [
        56,
        201
      ],
      "desenvolvida": [
        57
      ],
      "pelos": [
        58
      ],
      "autores,": [
        59
      ],
      "aplica": [
        61,
        203
      ],
      "mesma": [
        63,
        205
      ],
      "grafia": [
        64,
        206
      ],
      "para": [
        65,
        116,
        207
      ],
      "as": [
        66,
        167,
        208
      ],
      "primeiras": [
        67,
        209
      ],
      "sílabas": [
        68,
        210
      ],
      "nomes": [
        70,
        212
      ],
      "com": [
        71,
        85,
        88,
        94,
        144,
        213
      ],
      "o": [
        72,
        117,
        193,
        214
      ],
      "mesmo": [
        73,
        215
      ],
      "som.": [
        74
      ],
      "Procedemos": [
        75
      ],
      "ao": [
        76,
        114,
        156
      ],
      "base": [
        80,
        90,
        103
      ],
      "dados": [
        82
      ],
      "mortalidade": [
        84
      ],
      "59.065": [
        86
      ],
      "óbitos": [
        87,
        92
      ],
      "hospitalares": [
        93
      ],
      "531": [
        95
      ],
      "registros,": [
        96
      ],
      "apresentavam": [
        98
      ],
      "registro": [
        100
      ],
      "correspondente": [
        101
      ],
      "mortalidade.": [
        105
      ],
      "Diferentes": [
        106
      ],
      "estratégias": [
        107,
        168
      ],
      "foram": [
        110
      ],
      "comparadas": [
        111
      ],
      "em": [
        112,
        130,
        158,
        223
      ],
      "relação": [
        113
      ],
      "custo": [
        115
      ],
      "processamento": [
        118
      ],
      "proporção": [
        121
      ],
      "pares": [
        123,
        142,
        152,
        231
      ],
      "verdadeiros": [
        124,
        143
      ],
      "perdidos.": [
        125
      ],
      "estratégia": [
        127
      ],
      "múltiplos": [
        131
      ],
      "passos": [
        132
      ],
      "foi": [
        133,
        154
      ],
      "mais": [
        134
      ],
      "eficiente,": [
        135
      ],
      "permitindo": [
        136
      ],
      "identificação": [
        138
      ],
      "todos": [
        140
      ],
      "os": [
        141
      ],
      "formação": [
        146
      ],
      "número": [
        149
      ],
      "total": [
        150
      ],
      "inferior": [
        155
      ],
      "obtido": [
        157
      ],
      "duas": [
        159
      ],
      "rotinas": [
        160
      ],
      "passo": [
        163,
        170
      ],
      "único.": [
        164
      ],
      "Já": [
        165
      ],
      "entre": [
        166
      ],
      "único": [
        171
      ],
      "avaliadas,": [
        172
      ],
      "se": [
        175
      ],
      "baseou": [
        176
      ],
      "no": [
        177
      ],
      "emprego": [
        178
      ],
      "chave": [
        180
      ],
      "formada": [
        181
      ],
      "pela": [
        182
      ],
      "combinação": [
        183
      ],
      "código": [
        185
      ],
      "soundex": [
        186
      ],
      "primeiro": [
        188
      ],
      "nome": [
        189
      ],
      "sexo": [
        191
      ],
      "apresentou": [
        192,
        218
      ],
      "melhor": [
        194
      ],
      "resultado.": [
        195
      ],
      "som": [
        216
      ],
      "não": [
        217
      ],
      "impacto": [
        220
      ],
      "importante,": [
        221
      ],
      "quer": [
        222,
        225
      ],
      "custos,": [
        224
      ],
      "redução": [
        227
      ],
      "perda": [
        229
      ],
      "verdadeiros.": [
        232
      ]
    },
    "counts_by_year": [
      {
        "year": 2025,
        "cited_by_count": 2
      },
      {
        "year": 2022,
        "cited_by_count": 2
      },
      {
        "year": 2021,
        "cited_by_count": 3
      },
      {
        "year": 2020,
        "cited_by_count": 1
      },
      {
        "year": 2019,
        "cited_by_count": 2
      },
      {
        "year": 2018,
        "cited_by_count": 4
      },
      {
        "year": 2017,
        "cited_by_count": 2
      },
      {
        "year": 2016,
        "cited_by_count": 7
      },
      {
        "year": 2015,
        "cited_by_count": 3
      },
      {
        "year": 2014,
        "cited_by_count": 8
      },
      {
        "year": 2012,
        "cited_by_count": 2
      }
    ],
    "updated_date": "2026-02-05T00:54:17.221276",
    "created_date": "2016-06-24T00:00:00"
  }
]